{"Francisco":5.0,"Villa":6.0,"revolucionario":4.0,"pueblo":107.0,"Ánimo":6.0,"comenzando":1.0,"semana":18.0,"informar":15.0,"lunes":3.0,"avance":22.0,"Tren":20.0,"Maya":13.0,"acompañan":3.0,"gobernadores":21.0,"Tabasco":34.0,"RUTILIO":3.0,"gobernador":16.0,"Carlos":16.0,"MERINO":1.0,"gusto":9.0,"conferencia":5.0,"empezamos":4.0,"PROCURADOR":1.0,"federal":12.0,"Consumidor":4.0,"gasolina":1.0,"regular":1.0,"precio":23.0,"centavos":29.0,"litro":11.0,"Premium":4.0,"diésel":4.0,"Ven":2.0,"manteniendo":1.0,"debajo":3.0,"abajo":15.0,"referente":2.0,"país":83.0,"sido":18.0,"necesario":4.0,"dado":13.0,"presión":4.0,"internacionales":8.0,"mezcla":1.0,"mexicana":4.0,"petróleo":3.0,"corte":10.0,"agosto":17.0,"dólares":34.0,"dólar":5.0,"barril":3.0,"ayudan":4.0,"dé":2.0,"estabilidad":1.0,"Chevron":1.0,"Redco":1.0,"mientras":4.0,"aliadas":1.0,"consumidores":5.0,"G500":1.0,"BP":2.0,"Exxon":1.0,"Mobil":1.0,"tipo":16.0,"combustible":7.0,"tomando":3.0,"cuenta":30.0,"margen":10.0,"estaciones":7.0,"servicio":40.0,"carera":2.0,"Monterrey":6.0,"nuevo":18.0,"León":3.0,"público":22.0,"Vean":2.0,"promedio":6.0,"hablando":17.0,"dónde":13.0,"viene":8.0,"diferencia":8.0,"señores":1.0,"rosca":1.0,"cuatro":30.0,"ganando":5.0,"desvergonzados":1.0,"verdad":8.0,"alto":10.0,"consecutivas":1.0,"compárenlo":1.0,"bajo":5.0,"Umán":1.0,"Yucatán":4.0,"Cancún":5.0,"Quintana":4.0,"Roo":2.0,"encontramos":5.0,"económica":16.0,"Cintalapa":2.0,"CorpoGas":1.0,"Solidaridad":1.0,"comparados":1.0,"Tuxtla":1.0,"Gutiérrez":1.0,"Realizamos":1.0,"verificaciones":2.0,"correspondieron":1.0,"denuncias":1.0,"quejas":1.0,"presentaron":1.0,"saben":3.0,"través":16.0,"app":1.0,"gasolinera":2.0,"dejó":1.0,"verificar":4.0,"Tequisquiapan":2.0,"Querétaro":2.0,"tomen":1.0,"ocultando":1.0,"seguimos":1.0,"revisando":4.0,"sanitarios":1.0,"preferencia":5.0,"cobren":1.0,"condiciones":5.0,"gas":9.0,"LP":1.0,"convertimos":1.0,"internacional":11.0,"kilo":3.0,"cilindros":2.0,"regiones":10.0,"tanque":1.0,"estacionario":1.0,"respetaran":1.0,"respetándose":1.0,"verificamos":2.0,"constatamos":2.0,"encontrar":10.0,"siguen":8.0,"dándose":1.0,"pesar":8.0,"política":31.0,"estableció":1.0,"gobierno":106.0,"dando":9.0,"continúa":3.0,"ello":6.0,"Michoacán":2.0,"Jalisco":1.0,"Puebla":12.0,"Guerrero":21.0,"Sinaloa":9.0,"máximo":2.0,"América":24.0,"Atizapán":1.0,"ocho":10.0,"Guanajuato":1.0,"ejemplo":41.0,"S":3.0,"Tonatico":1.0,"región":12.0,"buen":21.0,"ahorro":5.0,"general":27.0,"buena":7.0,"situación":10.0,"reportar":5.0,"canasta":1.0,"básica":1.0,"consumen":4.0,"Índice":1.0,"Nacional":23.0,"Bebidas":1.0,"Alimentos":1.0,"alza":2.0,"afortunadamente":2.0,"reflejado":1.0,"menor":1.0,"proporción":2.0,"ligera":1.0,"verlos":2.0,"zona":22.0,"centro":17.0,"paquete":4.0,"caro":5.0,"Walmart":4.0,"Coyoacán":1.0,"Ciudad":24.0,"ojalá":2.0,"ayude":2.0,"mantenerlo":2.0,"Soriana":4.0,"Cuautitlán":1.0,"mismo":40.0,"mejorado":2.0,"Central":4.0,"Abastos":2.0,"Iztapalapa":3.0,"sigue":13.0,"Valle":2.0,"Paz":2.0,"Baja":4.0,"California":5.0,"Zacatecas":4.0,"norte":7.0,"Chihuahua":17.0,"pueden":19.0,"último":24.0,"sursureste":5.0,"Mérida":2.0,"vez":15.0,"quiere":16.0,"dar":15.0,"aliado":4.0,"Toca":1.0,"información":33.0,"heroínas":2.0,"héroes":2.0,"Unidos":48.0,"mandan":5.0,"cada":48.0,"mes":6.0,"mamá":2.0,"esposa":4.0,"acá":8.0,"Recuerden":4.0,"paisanas":1.0,"paisanos":4.0,"decide":2.0,"Cuánto":23.0,"llegar":11.0,"dependiendo":2.0,"canal":5.0,"escojas":2.0,"remesadora":1.0,"enviaron":2.0,"junio":1.0,"cinco":34.0,"millones":174.0,"pasado":9.0,"tendencia":1.0,"largo":9.0,"recurso":27.0,"recomendable":1.0,"efectivo":1.0,"uLink":2.0,"dio":17.0,"seis":12.0,"cobró":1.0,"comisión":5.0,"relativamente":2.0,"peor":5.0,"opción":1.0,"nueve":3.0,"busquen":1.0,"cobran":2.0,"mejor":21.0,"tomar":4.0,"envío":5.0,"depósito":1.0,"exactamente":5.0,"conviene":2.0,"menos":22.0,"lado":8.0,"mexicano":68.0,"comisiones":1.0,"buscar":5.0,"cercanos":1.0,"vivimos":1.0,"gasto":18.0,"extraordinario":5.0,"ir":37.0,"recoger":1.0,"remesa":4.0,"video":11.0,"laboratorio":2.0,"Profeco":4.0,"yogures":2.0,"beber":2.0,"VOZ":24.0,"realizó":2.0,"estudio":8.0,"calidad":8.0,"usan":1.0,"denominación":1.0,"yogurt":2.0,"fresa":4.0,"sabor":2.0,"especialistas":8.0,"revisaron":1.0,"contenido":4.0,"neto":1.0,"determinaron":1.0,"cantidad":9.0,"proteína":2.0,"grasa":1.0,"carbohidratos":1.0,"aporte":1.0,"calórico":1.0,"factor":1.0,"fundamental":8.0,"análisis":7.0,"bacterias":1.0,"benéficas":1.0,"vivas":1.0,"identificaron":1.0,"azúcares":5.0,"marca":13.0,"compararon":1.0,"etiqueta":4.0,"veraz":1.0,"represente":1.0,"engaño":2.0,"encontró":3.0,"contienen":2.0,"fruta":2.0,"cantidades":2.0,"Recuerda":1.0,"mayoría":14.0,"adiciona":1.0,"preparado":1.0,"normalmente":3.0,"contiene":1.0,"conservadores":9.0,"saborizantes":1.0,"acidulantes":1.0,"almidones":1.0,"colorantes":1.0,"importante":49.0,"leer":4.0,"saber":8.0,"llevamos":14.0,"mesa":2.0,"incluso":22.0,"dirigidas":1.0,"niñas":1.0,"niños":8.0,"edulcorantes":1.0,"sintéticos":1.0,"recomendados":1.0,"menores":3.0,"edad":3.0,"detector":1.0,"mostramos":2.0,"rebasan":1.0,"consumo":8.0,"diario":6.0,"gramos":1.0,"recomienda":1.0,"OMS":1.0,"logró":7.0,"industria":9.0,"cambiaria":1.0,"tal":3.0,"BNG":1.0,"Aliv":1.0,"Danone":1.0,"vio":4.0,"obligado":1.0,"cambiar":3.0,"sólo":36.0,"sino":34.0,"nombre":4.0,"anteriormente":1.0,"usaba":2.0,"término":6.0,"gastro":1.0,"sugería":1.0,"beneficio":16.0,"salud":45.0,"podía":1.0,"comprobar":1.0,"cumplió":1.0,"exige":1.0,"norma":1.0,"aunque":18.0,"hacía":4.0,"llamar":1.0,"natural":2.0,"encontraron":1.0,"añadidos":1.0,"presente":7.0,"mercado":11.0,"producto":8.0,"reformulado":1.0,"empodera":1.0,"haz":1.0,"razonado":1.0,"saludable":4.0,"MUJER":19.0,"Procuraduría":1.0,"transformación":20.0,"comienza":1.0,"casa":8.0,"Muchas":6.0,"JAVIER":2.0,"MAY":2.0,"Rodríguez":3.0,"DIRECTOR":4.0,"Fondo":8.0,"FOMENTO":1.0,"turismo":3.0,"permiso":16.0,"Hoy":9.0,"informamos":1.0,"tramo":14.0,"avanza":5.0,"obra":62.0,"Palenque":15.0,"Escárcega":8.0,"vía":18.0,"terminada":3.0,"complementarias":1.0,"previstas":1.0,"atención":20.0,"Visitantes":4.0,"próximo":5.0,"concluirse":1.0,"generado":5.0,"parte":44.0,"taller":4.0,"cochera":15.0,"contratiempo":1.0,"pruebas":1.0,"estáticas":1.0,"primer":11.0,"cuanto":8.0,"JOAO":2.0,"PEDRO":4.0,"PARREIRA":2.0,"Ejecutivo":5.0,"MOTA":1.0,"ENGIL":1.0,"LATINOAMÉRICA":1.0,"pequeño":3.0,"tendido":2.0,"sistema":26.0,"pórtico":3.0,"diferenciado":1.0,"razón":1.0,"demás":2.0,"mecánico":1.0,"poder":24.0,"extremamente":1.0,"acelerado":1.0,"capacidad":3.0,"ejecutar":2.0,"kilómetro":8.0,"medio":48.0,"garantizamos":1.0,"bastante":14.0,"podemos":21.0,"trabajar":7.0,"continuas":1.0,"próxima":2.0,"siempre":40.0,"enseñamos":2.0,"probablemente":1.0,"celebramos":2.0,"terminación":2.0,"viaducto":3.0,"Tenosique":3.0,"construcción":27.0,"estructura":6.0,"metálica":1.0,"hecha":4.0,"Guadalajara":4.0,"fabricación":2.0,"planta":15.0,"Recal":1.0,"transporte":3.0,"verificaron":1.0,"cimentación":3.0,"concreto":2.0,"urbanos":1.0,"solución":1.0,"permitió":2.0,"Candelaria":1.0,"previsibilidad":1.0,"social":33.0,"cruce":2.0,"ciudades":6.0,"recorrido":4.0,"explicamos":1.0,"fase":3.0,"nivelación":5.0,"después":12.0,"segunda":16.0,"tercera":4.0,"seguridad":39.0,"adecuada":1.0,"proceso":24.0,"ejecuta":2.0,"levanta":2.0,"escalera":2.0,"bateando":1.0,"balasto":1.0,"nivelando":1.0,"verificación":2.0,"geométrica":1.0,"ingeniera":1.0,"trabaja":2.0,"explica":1.0,"geometría":4.0,"férrea":3.0,"cirugía":1.0,"alta":3.0,"especificación":1.0,"componentes":1.0,"realmente":2.0,"ejecuten":1.0,"manera":46.0,"detallada":1.0,"exista":1.0,"ninguna":8.0,"posibilidad":10.0,"error":1.0,"poner":3.0,"señora":4.0,"contando":2.0,"historia":21.0,"tecnología":2.0,"certificación":1.0,"DANIA":1.0,"CONTRERAS":1.0,"TÉCNICA":1.0,"obteniendo":1.0,"diciendo":3.0,"comparando":2.0,"quisiera":14.0,"metro":3.0,"tan":15.0,"lejos":1.0,"valores":3.0,"proyecto":40.0,"seguir":22.0,"avanzando":6.0,"mujeres":23.0,"innovación":1.0,"enseñar":1.0,"estación":4.0,"reportando":3.0,"acabados":2.0,"misma":9.0,"terminamos":1.0,"quedar":11.0,"creo":23.0,"toda":86.0,"orgullo":5.0,"MAITE":1.0,"RAMOS":1.0,"GÓMEZ":1.0,"DIRECTORA":1.0,"ALSTOM":1.0,"hablar":8.0,"talleres":10.0,"jaguar":3.0,"refugiarse":1.0,"aire":1.0,"libre":8.0,"preservar":3.0,"vida":24.0,"útil":2.0,"enfocados":1.0,"reparaciones":1.0,"mantenimiento":8.0,"Imaginémonos":1.0,"gran":27.0,"hospital":5.0,"hospitales":6.0,"atender":20.0,"momento":13.0,"médicos":6.0,"medicina":3.0,"posible":6.0,"quirófano":1.0,"cado":2.0,"ubicados":3.0,"siguiente":22.0,"vemos":22.0,"ubicaciones":1.0,"podrán":3.0,"solamente":15.0,"Campeche":14.0,"Tulum":1.0,"Chetumal":2.0,"generando":1.0,"casi":15.0,"directos":4.0,"cuadrados":1.0,"operativos":2.0,"siete":13.0,"mejores":5.0,"ingenieros":4.0,"llamamos":1.0,"entrar":3.0,"nivel":6.0,"permiten":1.0,"trenes":8.0,"poquito":6.0,"usa":2.0,"carros":2.0,"arrastre":1.0,"obviamente":5.0,"manejar":1.0,"cargas":1.0,"pesadas":1.0,"recordar":5.0,"coche":3.0,"pesa":1.0,"toneladas":1.0,"equipamiento":4.0,"piezas":1.0,"cabinas":2.0,"pintura":6.0,"alguna":5.0,"contado":1.0,"Sahagún":1.0,"mantener":5.0,"condición":1.0,"guapo":2.0,"elevación":1.0,"inspeccionar":1.0,"power":1.0,"pack":1.0,"motores":1.0,"ruedas":3.0,"bogies":2.0,"presa":14.0,"desmontaje":1.0,"usamos":1.0,"utiliza":5.0,"quiero":10.0,"detenerme":1.0,"torno":3.0,"foso":3.0,"alineación":1.0,"balanceo":1.0,"reperfiladas":1.0,"forma":10.0,"operación":2.0,"garantizar":21.0,"fiabilidad":1.0,"disponibilidad":1.0,"cubriendo":1.0,"enfermeros":1.0,"darán":1.0,"cuidado":7.0,"duela":1.0,"absolutamente":7.0,"contar":3.0,"descansar":1.0,"revisiones":1.0,"chequeos":1.0,"establecido":1.0,"preventivo":2.0,"correctivo":1.0,"permitirá":3.0,"Construimos":1.0,"hecho":19.0,"actividades":17.0,"mayor":12.0,"actividad":10.0,"reparación":4.0,"subsistemas":1.0,"garantizan":2.0,"correcto":1.0,"funcionamiento":1.0,"DIEGO":1.0,"PRIETO":1.0,"HERNÁDEZ":1.0,"INSTITUTO":1.0,"ANTROPOLOGÍA":1.0,"INAH":4.0,"compañeras":2.0,"compañeros":9.0,"instituciones":18.0,"equipo":17.0,"articula":1.0,"futuro":7.0,"nueva":31.0,"mirada":2.0,"hacia":10.0,"presentar":10.0,"investigación":6.0,"arqueológica":4.0,"pilares":3.0,"fundamentales":8.0,"salvamento":1.0,"arqueológico":4.0,"permite":6.0,"identificar":3.0,"recuperar":2.0,"valiosa":1.0,"encontrando":1.0,"curso":2.0,"ferroviario":2.0,"fecha":10.0,"recuperado":1.0,"bienes":9.0,"inmuebles":1.0,"diferente":18.0,"carácter":2.0,"unidades":6.0,"habitacionales":1.0,"cimientos":1.0,"albarradas":1.0,"basamentos":1.0,"blancos":1.0,"sacbés":1.0,"territorio":8.0,"interesante":13.0,"involucra":1.0,"riviera":1.0,"Usumacinta":2.0,"lugar":18.0,"florecieron":1.0,"civilización":3.0,"muebles":1.0,"íntegros":1.0,"cerámica":3.0,"objeto":4.0,"piedra":2.0,"metates":1.0,"figurillas":1.0,"siendo":7.0,"analizados":1.0,"numerosos":1.0,"restauradores":2.0,"investigadores":1.0,"disciplinas":1.0,"incorporados":1.0,"rasgos":1.0,"asociados":1.0,"presencia":5.0,"programa":25.0,"mejoramiento":3.0,"sustento":1.0,"conservación":16.0,"patrimonio":12.0,"Moral":2.0,"Reforma":37.0,"Tigre":2.0,"periodo":4.0,"clásico":1.0,"podido":3.0,"ampliar":2.0,"visitables":1.0,"obtener":3.0,"cuales":8.0,"previstos":1.0,"Promeza":1.0,"señalética":3.0,"impresión":3.0,"habilitarla":1.0,"infraestructura":24.0,"avanzada":2.0,"Cuarta":4.0,"muestra":6.0,"reestructuración":1.0,"museo":2.0,"sito":1.0,"dedicado":5.0,"memoria":2.0,"arqueólogo":2.0,"cubano":1.0,"francés":1.0,"Alberto":2.0,"Ruz":1.0,"Lhuillier":1.0,"descubridor":1.0,"tumba":1.0,"reestructurar":1.0,"incorporando":1.0,"expuestos":1.0,"prácticamente":10.0,"terminado":1.0,"detalles":1.0,"gestión":3.0,"comunidades":23.0,"entorno":1.0,"puedan":7.0,"uso":7.0,"instalaciones":7.0,"favor":17.0,"conocida":2.0,"ofrecerá":3.0,"visita":5.0,"intensa":1.0,"prevalecía":1.0,"determinante":1.0,"senderismo":1.0,"encuentran":5.0,"encima":2.0,"instalar":3.0,"encuentra":6.0,"inicial":1.0,"abriendo":3.0,"Conjunto":1.0,"Triádico":1.0,"ofrecido":1.0,"considerable":4.0,"internes":1.0,"concluir":3.0,"presentarles":1.0,"solemos":1.0,"hacerlo":4.0,"hallazgo":4.0,"reciente":6.0,"ofrenda":5.0,"funeraria":1.0,"consistente":1.0,"cubierta":1.0,"platos":1.0,"bien":49.0,"contexto":3.0,"funerario":2.0,"vasija":2.0,"Boca":3.0,"considerablemente":3.0,"ancha":1.0,"ubicamos":1.0,"enterramiento":2.0,"persona":39.0,"joven":3.0,"determinando":1.0,"características":3.0,"punto":9.0,"vista":3.0,"antropofísico":1.0,"observar":1.0,"inferior":3.0,"izquierda":2.0,"entierro":1.0,"colocó":1.0,"elemento":4.0,"destacado":4.0,"habla":7.0,"importancia":6.0,"personaje":7.0,"anilló":1.0,"verde":3.0,"anillo":1.0,"jade":1.0,"Muchísimas":3.0,"María":5.0,"LUISA":2.0,"ALBORES":1.0,"González":5.0,"SECRETARIA":2.0,"primera":24.0,"construyendo":12.0,"haciendo":44.0,"ecosistemas":2.0,"Iniciamos":1.0,"Wanha":2.0,"reserva":7.0,"biosfera":5.0,"hectáreas":16.0,"ubica":3.0,"San":15.0,"Mártir":2.0,"río":12.0,"protegerá":1.0,"manglares":4.0,"agua":50.0,"dulce":1.0,"mundo":21.0,"adentro":1.0,"ubicadas":1.0,"Puerto":3.0,"Morelos":8.0,"área":16.0,"protección":16.0,"flora":9.0,"fauna":12.0,"contribuirá":1.0,"especies":7.0,"decretada":1.0,"julio":3.0,"promueven":1.0,"conectividad":4.0,"sitios":1.0,"poblaciones":3.0,"vuelve":2.0,"corredor":4.0,"biológico":2.0,"grande":22.0,"selva":7.0,"tropical":4.0,"Balam":2.0,"Kin":1.0,"NP":1.0,"estatal":4.0,"retoma":1.0,"federación":2.0,"destaca":2.0,"felinos":1.0,"Kú":1.0,"pasa":5.0,"contribuye":2.0,"murciélagos":2.0,"hábitat":2.0,"Báalam":1.0,"Beh":1.0,"conserva":1.0,"paso":7.0,"conecta":1.0,"laguna":3.0,"hacemos":9.0,"Calakmul":5.0,"pegado":1.0,"ampliación":2.0,"comentada":1.0,"millón":5.0,"semejando":1.0,"veces":36.0,"Tlaxcala":10.0,"mitad":10.0,"conservado":1.0,"Fonatur":2.0,"trabajando":18.0,"directamente":9.0,"entrega":4.0,"previos":1.0,"justificativos":1.0,"península":2.0,"Playa":2.0,"Delfines":1.0,"endémicas":2.0,"oso":1.0,"hormiguero":1.0,"maullador":1.0,"negro":1.0,"Jacinto":1.0,"Pat":1.0,"relevante":10.0,"biodiversidad":3.0,"aves":1.0,"pasan":1.0,"espacio":14.0,"Buenaventura":1.0,"movilidad":1.0,"habitan":1.0,"lagunar":1.0,"Nichupté":1.0,"categoría":1.0,"comunidad":10.0,"núcleo":1.0,"agrario":1.0,"sumando":2.0,"trabajo":71.0,"instrumentos":4.0,"enfoque":1.0,"construyen":1.0,"aseguran":1.0,"creación":14.0,"vivos":2.0,"ambiental":4.0,"Compartirles":2.0,"ordenamiento":3.0,"ecológico":3.0,"local":3.0,"plan":37.0,"manejo":8.0,"inversiones":10.0,"sociales":6.0,"cuestiones":3.0,"ambientales":3.0,"erogado":1.0,"coadyuvan":1.0,"capacitación":4.0,"comunitaria":3.0,"incidencia":2.0,"lugares":3.0,"forestales":3.0,"igual":9.0,"Forestal":4.0,"erogación":1.0,"activa":2.0,"protegiendo":3.0,"comunitario":1.0,"trabajamos":3.0,"macizos":1.0,"brigadas":1.0,"vigilancia":2.0,"prevención":7.0,"combate":3.0,"incendios":3.0,"participan":1.0,"ejidos":1.0,"capacitadas":1.0,"capacitados":1.0,"Sembrando":2.0,"sabemos":5.0,"planeta":1.0,"Tierra":2.0,"reforestación":2.0,"coadyuva":1.0,"sembradoras":1.0,"sembradores":1.0,"favoreciendo":1.0,"regeneración":1.0,"captación":3.0,"aumento":8.0,"biológica":1.0,"tiempo":35.0,"rescatar":4.0,"inversión":31.0,"anual":4.0,"cuáles":3.0,"hacen":10.0,"favorecer":1.0,"tránsito":1.0,"seguro":6.0,"asegurar":2.0,"cuentan":3.0,"seguramente":2.0,"vehiculares":1.0,"ganaderos":1.0,"peatonales":1.0,"drenaje":1.0,"trasversal":1.0,"comparto":1.0,"adelante":14.0,"responder":1.0,"reto":1.0,"sostenible":2.0,"amigable":1.0,"naturaleza":3.0,"sintonía":1.0,"artículo":4.0,"4º":1.0,"Constitución":20.0,"derecho":23.0,"humano":7.0,"sano":1.0,"desarrollo":30.0,"bienestar":8.0,"acciones":40.0,"detener":4.0,"impacto":6.0,"empresa":34.0,"Calica":1.0,"contaminación":1.0,"suelo":3.0,"oficial":1.0,"Ginebra":1.0,"Suiza":1.0,"oficina":1.0,"comisionada":1.0,"Naciones":1.0,"manifestar":1.0,"preocupación":2.0,"desastre":7.0,"causado":1.0,"presentó":8.0,"11º":1.0,"Foro":1.0,"dictamen":2.0,"diagnóstico":1.0,"porcícola":1.0,"implicaciones":1.0,"realizar":3.0,"coordinado":2.0,"problemática":1.0,"oportuna":1.0,"cobertura":8.0,"desarrolló":1.0,"Piloto":2.0,"Alertas":1.0,"Tempranas":1.0,"Deforestación":2.0,"Control":2.0,"coordinación":3.0,"realizado":6.0,"incluyendo":2.0,"filtros":1.0,"revisión":4.0,"inspecciones":1.0,"predios":1.0,"aserraderos":1.0,"especiales":2.0,"detectar":1.0,"malas":1.0,"crecimiento":11.0,"frontera":23.0,"agropecuaria":1.0,"busca":6.0,"expedir":1.0,"declaratoria":6.0,"establecer":2.0,"restauración":11.0,"ecológica":1.0,"evitar":5.0,"afectaciones":2.0,"cuerpos":1.0,"lleva":15.0,"cabo":27.0,"plantaciones":1.0,"palma":1.0,"africana":1.0,"dentro":4.0,"regula":4.0,"agrotóxicos":1.0,"Mediante":1.0,"generación":2.0,"coadyuven":1.0,"preservación":4.0,"reitera":1.0,"compromiso":6.0,"impulsar":3.0,"promover":5.0,"responsables":1.0,"cuidar":4.0,"BLAS":1.0,"NÚÑEZ":1.0,"JORDÁN":1.0,"JEFE":1.0,"COORDINADOR":3.0,"OPERACIONES":1.0,"CCO":1.0,"DIRECCIÓN":2.0,"SECRETARÍA":2.0,"DEFENSA":3.0,"SEDENA":1.0,"hotel":1.0,"localizado":1.0,"frente":13.0,"cerca":8.0,"presenta":5.0,"ejecutan":2.0,"terreno":2.0,"muros":4.0,"contención":1.0,"estabilización":1.0,"taludes":1.0,"estacionamiento":1.0,"alberca":1.0,"edificio":7.0,"principalmente":2.0,"trabajadores":9.0,"genera":3.0,"derrama":1.0,"localidad":1.0,"Asimismo":6.0,"Mitigación":1.0,"considerado":2.0,"árboles":1.0,"endémicos":1.0,"junto":8.0,"construye":1.0,"participación":9.0,"mayoritaria":1.0,"administración":8.0,"logísticas":1.0,"principal":15.0,"programada":1.0,"inauguración":1.0,"finales":3.0,"trae":5.0,"integral":3.0,"desafío":1.0,"ingeniería":1.0,"alegres":1.0,"magna":2.0,"falta":23.0,"subamos":1.0,"emocionados":1.0,"visión":4.0,"patriotismo":1.0,"estadista":1.0,"casualidad":1.0,"consolidación":1.0,"pública":30.0,"entidad":6.0,"corazón":6.0,"maravillas":1.0,"cultura":11.0,"invitamos":1.0,"recorramos":1.0,"conozcamos":1.0,"paraíso":1.0,"entrelaza":1.0,"maravillosos":1.0,"diversidad":3.0,"milenarios":1.0,"realizan":1.0,"tradiciones":1.0,"herencia":1.0,"ancestral":3.0,"mencionar":7.0,"Cristóbal":2.0,"bosque":2.0,"Comitán":2.0,"Domínguez":5.0,"lagos":1.0,"Montebello":1.0,"diversos":3.0,"colores":3.0,"arquitectónica":1.0,"ruinas":2.0,"cascadas":1.0,"quedan":3.0,"Chiapa":22.0,"Corzo":1.0,"Mágico":2.0,"bañado":1.0,"municipio":34.0,"bañada":1.0,"imponente":1.0,"Grijalva":1.0,"danzas":1.0,"parachicos":1.0,"Cañón":3.0,"Sumidero":1.0,"transparente":2.0,"limpio":5.0,"conocerlo":2.0,"aventura":1.0,"mágica":2.0,"impetuosas":1.0,"restaurando":2.0,"República":4.0,"lucir":1.0,"esplendor":2.0,"belleza":3.0,"Copainalá":1.0,"Ocozocoautla":1.0,"cultural":20.0,"originarios":1.0,"llegada":1.0,"vagones":1.0,"maquinaria":1.0,"materia":6.0,"educación":13.0,"empleo":14.0,"entrelazar":1.0,"línea":8.0,"K":1.0,"sur":10.0,"Tapachula":1.0,"costa":3.0,"valor":8.0,"agregado":1.0,"producimos":1.0,"crece":2.0,"invitar":1.0,"veamos":1.0,"corto":6.0,"significativo":1.0,"espera":4.0,"brazos":1.0,"PROYECCIÓN":1.0,"honor":3.0,"acompañarlo":1.0,"nuevamente":1.0,"exponer":1.0,"estratégico":3.0,"positivo":1.0,"fechan":1.0,"aseguro":1.0,"transformado":1.0,"adversidad":1.0,"prosperidad":2.0,"pleno":1.0,"constructivo":1.0,"detonado":1.0,"reactivado":1.0,"economía":17.0,"mejorando":2.0,"rostro":2.0,"conciliación":1.0,"progreso":7.0,"debe":18.0,"impulso":3.0,"permitido":5.0,"convierta":1.0,"atractivo":2.0,"sector":9.0,"privado":2.0,"refleja":2.0,"repunte":3.0,"alrededor":2.0,"trimestre":1.0,"formales":1.0,"turística":3.0,"económico":7.0,"ayudará":1.0,"conectar":1.0,"Interoceánico":7.0,"polos":1.0,"sinónimo":1.0,"libertad":12.0,"democracia":11.0,"visible":1.0,"edén":1.0,"emblemático":3.0,"sinigual":1.0,"poseedor":2.0,"actores":1.0,"principales":4.0,"traerá":1.0,"millonarias":1.0,"permitirán":1.0,"mayores":2.0,"fuentes":3.0,"par":1.0,"produciendo":1.0,"voluntades":1.0,"anuncio":4.0,"japonesa":1.0,"Sumitomo":1.0,"Electric":1.0,"Wiring":1.0,"Systems":1.0,"producción":2.0,"Site":1.0,"especializada":1.0,"arneses":1.0,"eléctricos":1.0,"vehículos":1.0,"ventajas":1.0,"competitivas":1.0,"ofrece":1.0,"estímulos":1.0,"fiscales":2.0,"fronterizos":1.0,"Balancán":1.0,"aplicables":1.0,"IVA":2.0,"ISR":1.0,"envidiable":1.0,"posición":1.0,"geográfica":1.0,"consolida":2.0,"nodo":1.0,"logístico":1.0,"conectará":1.0,"facilitando":1.0,"traslado":4.0,"energética":1.0,"canales":4.0,"comercialización":1.0,"ganadera":1.0,"agrícolas":1.0,"expansión":1.0,"artesanal":1.0,"venta":1.0,"exportación":1.0,"Istmo":5.0,"Tehuantepec":5.0,"Chontalpa":1.0,"atracción":1.0,"sustentable":1.0,"Pantanos":1.0,"Centla":1.0,"detonantes":1.0,"promoción":1.0,"bondades":1.0,"justa":1.0,"humanista":1.0,"licenciado":1.0,"dejar":10.0,"atrás":3.0,"desarrolla":3.0,"sólida":2.0,"disminución":19.0,"pobreza":48.0,"reconciliado":1.0,"vocaciones":1.0,"productivas":1.0,"generar":3.0,"profundos":3.0,"destino":2.0,"elevan":1.0,"tabasqueños":2.0,"preparando":1.0,"lista":3.0,"primero":23.0,"Nancy":1.0,"Oro":2.0,"Sólido":1.0,"Empuje":1.0,"Migrante":2.0,"opinión":7.0,"relación":9.0,"INE":18.0,"censurar":1.0,"bajar":4.0,"borrar":1.0,"reportajes":3.0,"aspirantes":2.0,"movimiento":8.0,"Radio":1.0,"Televisión":1.0,"específicamente":1.0,"consejera":1.0,"Claudia":1.0,"Zavala":1.0,"sucediendo":7.0,"pienso":1.0,"revisar":1.0,"seriedad":1.0,"facultades":2.0,"Tribunal":1.0,"Electoral":1.0,"afecten":1.0,"invadan":1.0,"corresponden":2.0,"poderes":1.0,"garantice":2.0,"manifestación":2.0,"límite":1.0,"nadie":8.0,"expresarse":1.0,"manifestarse":1.0,"decíamos":1.0,"sostenemos":1.0,"prohibido":1.0,"prohibir":1.0,"época":7.0,"liberales":1.0,"prensa":14.0,"ejercer":1.0,"censura":1.0,"corresponde":10.0,"vienen":11.0,"antiguo":1.0,"régimen":7.0,"respetar":6.0,"decisiones":3.0,"aun":4.0,"francamente":1.0,"constitucionales":1.0,"pensar":4.0,"necesidad":6.0,"avanzado":6.0,"limpiar":4.0,"corrupción":22.0,"reducto":1.0,"oligárquico":1.0,"ayuda":20.0,"conservadurismo":5.0,"Acaba":3.0,"conocer":27.0,"ministro":16.0,"distribuir":6.0,"texto":27.0,"especial":5.0,"gobernadora":16.0,"reaccionaria":1.0,"conservadora":3.0,"irresponsable":5.0,"politiquera":1.0,"controversia":6.0,"entreguen":2.0,"estudiantes":5.0,"deshonesto":2.0,"ordena":1.0,"distribuyan":3.0,"buscando":2.0,"decisión":3.0,"facultad":4.0,"elaboración":1.0,"distribución":11.0,"mandato":2.0,"constitucional":7.0,"llamando":1.0,"ciudadanos":3.0,"piensen":3.0,"renovación":1.0,"electos":1.0,"cúpula":8.0,"político":9.0,"elige":2.0,"diputados":1.0,"senadores":1.0,"elija":3.0,"requerir":1.0,"pueda":4.0,"llevar":21.0,"necesita":15.0,"calificada":1.0,"simple":1.0,"votos":1.0,"decidir":6.0,"elecciones":16.0,"votar":7.0,"fundamentalmente":1.0,"nación":6.0,"mantenga":1.0,"regresen":3.0,"fueros":1.0,"gobernaban":1.0,"minoría":8.0,"rapaz":2.0,"continúe":9.0,"consolide":1.0,"establezca":1.0,"auténtica":2.0,"viendo":16.0,"contento":10.0,"venido":1.0,"satisfecho":1.0,"podría":12.0,"iría":1.0,"logrado":3.0,"retirar":1.0,"morir":1.0,"tranquilo":2.0,"imagínense":5.0,"sueño":1.0,"buscábamos":1.0,"ideal":4.0,"redujera":1.0,"disminuyera":1.0,"desigualdad":22.0,"resulta":6.0,"logramos":4.0,"salido":3.0,"pandemia":7.0,"crisis":21.0,"población":26.0,"habitantes":3.0,"Aproximadamente":1.0,"dejaron":2.0,"años":35.0,"conste":1.0,"dedicaron":7.0,"vender":1.0,"entregar":10.0,"suponía":1.0,"privatización":3.0,"convertir":1.0,"manejara":1.0,"presupuesto":43.0,"entregaron":8.0,"bancos":4.0,"ferrocarriles":1.0,"minas":1.0,"ejidales":1.0,"aeropuertos":5.0,"avanzaron":2.0,"eléctrica":1.0,"justificó":1.0,"Salinas":6.0,"privatizaciones":1.0,"libro":30.0,"hizo":14.0,"publicó":5.0,"profesional":3.0,"técnico":6.0,"actuó":1.0,"secretario":24.0,"organismo":7.0,"apellido":1.0,"Rogozinski":3.0,"vendieron":1.0,"consiguen":1.0,"objetivo":4.0,"llamaban":2.0,"desincorporación":1.0,"eufemismo":1.0,"financiar":1.0,"opuesto":3.0,"llama":7.0,"segundo":10.0,"capítulo":1.0,"tercero":4.0,"justifican":1.0,"número":16.0,"remataron":1.0,"resultado":18.0,"redujo":13.0,"contrario":3.0,"concentración":1.0,"dinero":16.0,"unas":6.0,"cuantas":1.0,"manos":1.0,"empobreció":1.0,"estrategia":7.0,"ayudar":12.0,"destinar":3.0,"base":2.0,"pirámide":2.0,"arriba":18.0,"equivoque":1.0,"Calderón":4.0,"recibió":1.0,"muchísimo":13.0,"barriles":1.0,"extraían":1.0,"Entró":1.0,"dato":24.0,"ricos":3.0,"llegaron":5.0,"ingresos":3.0,"aumentan":1.0,"aumenta":3.0,"salario":5.0,"reduce":6.0,"tampoco":14.0,"significa":7.0,"mal":6.0,"utilidades":1.0,"equivoqué":1.0,"parezco":1.0,"calderonista":1.0,"Miren":5.0,"Nunca":1.0,"gente":47.0,"corruptos":2.0,"sabes":2.0,"caminar":1.0,"cambio":13.0,"haga":3.0,"realidad":4.0,"camino":8.0,"claras":2.0,"medias":1.0,"tintas":1.0,"justo":1.0,"querer":6.0,"retroceso":1.0,"jerarca":1.0,"leído":4.0,"Oye":2.0,"primo":1.0,"hermano":2.0,"mentalidad":1.0,"retrógrada":1.0,"culpa":2.0,"todavía":16.0,"verse":1.0,"opinan":1.0,"madres":6.0,"padres":5.0,"familia":11.0,"rechazar":1.0,"dirigente":5.0,"PAN":12.0,"llegó":5.0,"arrancaran":1.0,"hojas":2.0,"arrancar":1.0,"politiquería":3.0,"queriendo":1.0,"manipular":3.0,"tomado":1.0,"conciencia":1.0,"precisamente":4.0,"privatizador":1.0,"concesiones":3.0,"pedir":6.0,"publicado":2.0,"varios":8.0,"José":10.0,"Gurría":5.0,"ahorita":4.0,"encargado":5.0,"bloque":2.0,"opositor":6.0,"impulsor":1.0,"Grupo":5.0,"Xcaret":1.0,"Gortari":6.0,"operó":1.0,"préstamos":3.0,"volvió":1.0,"facilitador":1.0,"turno":2.0,"empezó":2.0,"frecuentes":1.0,"raíz":3.0,"restricciones":1.0,"limitado":3.0,"tras":1.0,"evidente":1.0,"depredación":1.0,"intereses":1.0,"seriamente":1.0,"tráfico":1.0,"influencias":1.0,"Lulú":1.0,"Pali":2.0,"hermana":1.0,"aparece":6.0,"dueño":1.0,"Miguel":4.0,"accionistas":1.0,"sombra":1.0,"operar":1.0,"respecto":10.0,"conoce":5.0,"explotación":2.0,"materiales":5.0,"Carmen":1.0,"bellísima":1.0,"Caribe":7.0,"extracción":1.0,"grava":1.0,"llevársela":1.0,"construir":6.0,"enojo":1.0,"seudoambientalistas":1.0,"lanzaron":1.0,"fuerte":7.0,"conocido":5.0,"Hacienda":18.0,"aprobó":4.0,"Fobaproa":4.0,"privadas":1.0,"empresarios":1.0,"banqueros":1.0,"convirtieran":1.0,"deuda":8.0,"conocía":4.0,"dependencia":1.0,"causa":4.0,"daño":1.0,"billones":1.0,"elaborando":2.0,"conservador":7.0,"simulación":1.0,"hacían":2.0,"pasar":2.0,"progresistas":2.0,"progres":1.0,"ondita":1.0,"moderna":2.0,"contrapuestos":1.0,"Prianpara":1.0,"escogido":1.0,"recién":1.0,"egresado":2.0,"ITAM":1.0,"Harvard":1.0,"costado":1.0,"aclarar":2.0,"piensa":5.0,"oligarquía":3.0,"costaría":3.0,"dilucidar":1.0,"declarar":2.0,"iban":8.0,"tardar":2.0,"reconocer":5.0,"acertó":1.0,"dominando":2.0,"pasaron":1.0,"dominaron":1.0,"faramalla":1.0,"continuó":1.0,"hablamos":3.0,"gatopardismo":1.0,"apariencia":1.0,"cambian":1.0,"desgastando":1.0,"PRI":1.0,"engañaron":1.0,"candidato":7.0,"supuestamente":2.0,"representaba":1.0,"siguió":1.0,"distinto":8.0,"vaya":6.0,"aplicando":3.0,"agrupan":1.0,"gerente":2.0,"hijo":4.0,"emula":1.0,"papá":3.0,"participó":1.0,"fraude":1.0,"coordina":1.0,"manipulación":3.0,"increíble":3.0,"mentirosos":1.0,"calumniadores":1.0,"enseñando":1.0,"cobre":1.0,"periodistas":1.0,"intelectuales":1.0,"orgánicos":1.0,"acomodaticios":1.0,"vivían":2.0,"amparo":11.0,"lanzados":1.0,"consciente":3.0,"funcionado":3.0,"disminuir":2.0,"delictiva":1.0,"relaciones":4.0,"Canadá":5.0,"Centroamérica":5.0,"Latina":2.0,"golondrina":1.0,"verano":1.0,"concierto":1.0,"caminando":1.0,"cónsul":1.0,"Sacramento":1.0,"Christian":1.0,"Tonatiuh":1.0,"Jiménez":1.0,"Cheapas":1.0,"perdón":2.0,"nombramientos":2.0,"ve":5.0,"ocasión":3.0,"pedido":1.0,"pudieran":3.0,"venir":4.0,"cónsules":2.0,"informarle":4.0,"instrucción":1.0,"recibiendo":8.0,"canciller":1.0,"Alicia":1.0,"Bárcena":1.0,"quedamos":2.0,"migratoria":3.0,"aprovechar":1.0,"conteste":3.0,"inquietud":1.0,"Liliana":2.0,"quedó":4.0,"com":1.0,"mx":2.0,"Puente":2.0,"Suprema":2.0,"resolverá":1.0,"influirá":1.0,"resolución":2.0,"conflicto":3.0,"expuse":1.0,"repito":7.0,"autoridad":1.0,"considero":3.0,"actuando":1.0,"fines":1.0,"politiqueros":2.0,"mostrando":1.0,"extremo":1.0,"consta":1.0,"adversario":2.0,"resolvió":1.0,"cumplir":4.0,"violatorio":2.0,"elaborar":1.0,"distribuirlos":2.0,"continuar":4.0,"legal":2.0,"reaccionarios":1.0,"queden":2.0,"Apelará":1.0,"fallo":1.0,"esperar":5.0,"resuelven":4.0,"definitiva":1.0,"gustaría":4.0,"opinaran":1.0,"redes":4.0,"CUEVAS":19.0,"página":3.0,"Conaliteg":1.0,"decidan":1.0,"cuándo":1.0,"consulta":7.0,"resuelvan":1.0,"distribuyendo":1.0,"distribuidos":2.0,"promovieron":1.0,"distribuimos":1.0,"escuelas":1.0,"dicho":2.0,"juntan":1.0,"maestros":1.0,"pidiendo":1.0,"reclamándole":1.0,"esperarnos":2.0,"temas":14.0,"aborden":1.0,"polarizan":1.0,"politiza":1.0,"cosa":23.0,"noble":1.0,"oficio":1.0,"servidor":5.0,"servir":1.0,"práctica":4.0,"amor":5.0,"prójimo":1.0,"Hablan":2.0,"comunismo":14.0,"palabra":4.0,"entenderán":1.0,"definición":5.0,"darle":10.0,"según":5.0,"necesidades":8.0,"papa":1.0,"cristianismo":1.0,"primitivo":1.0,"Cristo":1.0,"potentados":1.0,"acuerdo":14.0,"poderosos":1.0,"seguían":1.0,"espiaban":1.0,"agitador":1.0,"crucificaron":1.0,"Defender":2.0,"pobre":25.0,"comunista":12.0,"evangelio":3.0,"revisen":1.0,"siquiera":3.0,"fragmento":4.0,"poema":5.0,"respetuosos":1.0,"esperando":3.0,"destruyan":1.0,"quedemos":2.0,"cruzados":1.0,"lleven":7.0,"judío":3.0,"católico":3.0,"evangélico":4.0,"solo":2.0,"Necesitamos":1.0,"Independientemente":2.0,"librepensador":1.0,"respetarnos":1.0,"amarnos":1.0,"manipulador":1.0,"acuerdan":2.0,"decían":3.0,"ganábamos":1.0,"iba":15.0,"fuga":1.0,"capital":6.0,"devaluación":1.0,"íbamos":1.0,"quitar":1.0,"Parece":1.0,"mentira":22.0,"campaña":4.0,"enfrentamos":1.0,"peligro":1.0,"Loret":3.0,"Mola":3.0,"comprar":4.0,"dolaritos":1.0,"calculaban":1.0,"experto":2.0,"ufana":1.0,"neoliberal":11.0,"Leo":1.0,"Zuckermann":2.0,"Pon":1.0,"entrevista":1.0,"escuchado":1.0,"ofrezca":1.0,"disculpas":3.0,"peso":33.0,"devaluar":1.0,"sucedido":3.0,"entiendo":5.0,"molestia":2.0,"quisieran":1.0,"privilegios":2.0,"colmados":1.0,"atenciones":2.0,"ganan":14.0,"mensuales":3.0,"fideicomiso":3.0,"jardineros":1.0,"resolver":8.0,"Luz":1.0,"ley":6.0,"aplicar":3.0,"injusto":1.0,"retorcer":1.0,"pisoteen":1.0,"deja":3.0,"cuesta":8.0,"Hans":2.0,"Salazar":2.0,"Noticiero":3.0,"propósito":3.0,"registrando":2.0,"ventilación":1.0,"discusión":1.0,"posiciones":1.0,"ciertos":1.0,"posturas":1.0,"marcadas":2.0,"citar":1.0,"pasó":2.0,"fin":12.0,"Argentina":14.0,"Milei":2.0,"ultraconservador":1.0,"ultraderechista":2.0,"fuerza":1.0,"sorprendido":2.0,"urnas":3.0,"enfila":2.0,"ganado":1.0,"presidencia":1.0,"sudamericano":1.0,"enfocarse":1.0,"concretamente":1.0,"lectura":1.0,"giro":1.0,"ocurre":1.0,"extrapolar":1.0,"experiencias":1.0,"distinta":4.0,"idiosincrasia":2.0,"embargo":9.0,"afectado":10.0,"derecha":4.0,"Macri":3.0,"endeudó":1.0,"completo":5.0,"complicidad":1.0,"Monetario":2.0,"dieron":4.0,"rebasando":1.0,"pago":1.0,"querían":2.0,"continuara":1.0,"gana":5.0,"Fernández":1.0,"queda":8.0,"enorme":4.0,"espalda":2.0,"corresponsables":1.0,"endeudamiento":1.0,"precipitó":1.0,"afectó":1.0,"produjo":1.0,"inflación":3.0,"Hitler":2.0,"padeció":1.0,"llegara":1.0,"autoritario":1.0,"inflaciones":1.0,"pasando":10.0,"eh":2.0,"aclare":1.0,"referencia":7.0,"histórica":3.0,"causó":1.0,"Agréguenle":1.0,"faltó":2.0,"digo":9.0,"respetuosa":3.0,"cariñosa":1.0,"zigzaguearon":1.0,"demasiado":1.0,"anclarse":1.0,"zigzaguear":1.0,"termina":1.0,"quedando":3.0,"gobernar":1.0,"apoyo":24.0,"guiar":1.0,"venimos":4.0,"amante":1.0,"Apóstol":1.0,"enfrentó":1.0,"golpismo":1.0,"Huerta":1.0,"descarada":1.0,"embajador":2.0,"preferible":1.0,"olvidar":3.0,"detienen":1.0,"Madero":5.0,"Palacio":5.0,"sale":6.0,"balcón":1.0,"desatendida":1.0,"predicara":1.0,"desierto":1.0,"desentendida":1.0,"pudo":1.0,"alianza":1.0,"campesinos":1.0,"zapatistas":1.0,"enfrentar":5.0,"pandilla":1.0,"rufianes":1.0,"única":2.0,"triunfara":1.0,"democrático":1.0,"enseñanza":1.0,"existe":9.0,"mañaneras":1.0,"absoluto":1.0,"Clarín":3.0,"plural":1.0,"Mercurio":1.0,"Chile":11.0,"dominan":1.0,"parecido":3.0,"Televisa":3.0,"derechoso":1.0,"mediática":3.0,"fuertísima":1.0,"levantaron":1.0,"dices":1.0,"elección":15.0,"presidencial":9.0,"pendiente":1.0,"leía":1.0,"reacciones":1.0,"botepronto":2.0,"jóvenes":31.0,"votaron":1.0,"parecer":1.0,"circunstancias":1.0,"lee":1.0,"confrontación":1.0,"interna":2.0,"válida":1.0,"polémicas":1.0,"septiembre":1.0,"definir":1.0,"coordinadora":1.0,"unidad":5.0,"completa":1.0,"mirado":2.0,"observado":1.0,"culminar":1.0,"mandar":4.0,"obedeciendo":3.0,"legítimas":1.0,"aspiraciones":1.0,"personales":1.0,"prevalecer":1.0,"interés":8.0,"ningún":7.0,"problema":12.0,"partido":14.0,"hombres":19.0,"última":9.0,"encuesta":16.0,"traigo":1.0,"jueves":3.0,"telefónica":1.0,"teléfono":1.0,"aceptación":1.0,"visto":9.0,"cuchareadas":1.0,"serias":1.0,"cuál":9.0,"división":1.0,"polarización":2.0,"multar":1.0,"cepillar":1.0,"apoyando":4.0,"total":14.0,"merecen":2.0,"respeto":10.0,"disentir":1.0,"oposición":7.0,"asunto":8.0,"actuar":3.0,"asesor":3.0,"enojan":2.0,"mire":1.0,"documental":5.0,"relaciona":1.0,"conoció":1.0,"Mataviejitas":1.0,"dama":1.0,"silencio":2.0,"documentalista":3.0,"sepa":1.0,"enfocarme":1.0,"sucedió":1.0,"Araceli":1.0,"Vázquez":2.0,"cárcel":8.0,"principio":2.0,"propio":3.0,"pensaba":2.0,"cometía":1.0,"crímenes":2.0,"reconoce":1.0,"robaba":2.0,"asaltaba":1.0,"adulta":2.0,"algún":10.0,"particular":10.0,"asesinato":5.0,"oportunidad":2.0,"creó":6.0,"llamó":3.0,"Aracely":1.0,"detención":3.0,"señalada":1.0,"acreditaron":1.0,"preguntar":1.0,"partir":10.0,"petición":1.0,"propia":1.0,"pudiera":6.0,"revisarse":1.0,"compete":1.0,"fiscalía":2.0,"encaminado":1.0,"casos":10.0,"presentado":1.0,"ido":1.0,"empieza":2.0,"finalmente":7.0,"intento":3.0,"despojo":1.0,"Escondido":1.0,"traje":3.0,"comentado":5.0,"Oaxaca":18.0,"pidió":2.0,"viera":1.0,"padeciendo":1.0,"negocio":14.0,"propiedad":1.0,"planteado":3.0,"planteamientos":3.0,"agradezco":4.0,"pedimos":1.0,"corresponda":1.0,"reúna":2.0,"informó":7.0,"pedirle":1.0,"Laura":3.0,"Salomón":1.0,"Jara":1.0,"tarde":11.0,"hora":4.0,"desayuno":1.0,"puedo":7.0,"desayunar":5.0,"Beatriz":3.0,"reuniones":3.0,"varias":5.0,"reunión":11.0,"SEP":3.0,"seguirlos":1.0,"antier":1.0,"viernes":3.0,"comprobé":1.0,"hicieron":6.0,"atribuyendo":1.0,"Brecht":1.0,"pensaban":1.0,"pastor":1.0,"frase":7.0,"luterano":1.0,"ponla":1.0,"crédito":1.0,"fíjense":1.0,"profesionales":2.0,"luchan":5.0,"ponlo":1.0,"requiere":6.0,"relevo":1.0,"generacional":1.0,"continuidad":2.0,"interrumpida":1.0,"imprescindibles":2.0,"vayan":11.0,"cansar":1.0,"Tren Maya":28.0,"ESCANDÓN CADENAS":8.0,"RICARDO SHEFFIELD":3.0,"SHEFFIELD PADILLA":2.0,"semana pasada":3.0,"gasolina regular":3.0,"pesos centavos":8.0,"incentivo fiscal":2.0,"Petro Seven":4.0,"franquicia Pemex":3.0,"centavos mientras":6.0,"precio máximo":4.0,"tipo cambiario":3.0,"INICIA VIDEO":4.0,"FINALIZA VIDEO":4.0,"próxima lámina":3.0,"seguir avanzando":3.0,"jaguar rodante":4.0,"lámina vemos":3.0,"senderos interpretativos":2.0,"medio ambiente":3.0,"áreas naturales":8.0,"naturales protegidas":8.0,"natural protegida":3.0,"destinadas voluntariamente":2.0,"comunitarios participativos":2.0,"reales útiles":2.0,"cuidado ambiental":4.0,"núcleos agrarios":4.0,"Naciones Unidas":2.0,"Tala Ilegal":2.0,"Cuarta Transformación":5.0,"arquitectura colonial":2.0,"sur sureste":4.0,"brazos abiertos":2.0,"MERINO CAMPOS":2.0,"refinería Olmeca":2.0,"Poder Judicial":15.0,"ministro deshonesto":3.0,"jueces magistrados":2.0,"cinco millones":4.0,"crisis económica":4.0,"RUTILIO CRUZ":5.0,"CRUZ ESCANDÓN":5.0,"José Ángel":6.0,"Ángel Gurría":6.0,"Grupo Xcaret":4.0,"bloque conservador":4.0,"Claudio X":2.0,"honrosas excepciones":2.0,"Liliana Piña":2.0,"Luis María":4.0,"María Aguilar":5.0,"Pueblo Pueblo":7.0,"Rosa Icela":4.0,"Bertolt Brecht":3.0,"Buenas":2.0,"hoy":40.0,"martes":1.0,"Pulso":3.0,"mejorar":7.0,"reconstrucción":16.0,"vivienda":17.0,"temblor":4.0,"temblores":4.0,"llevado":2.0,"Poder":8.0,"terminar":7.0,"diciembre":6.0,"acompaña":1.0,"jefe":12.0,"gobernadorade":1.0,"Chiapas":13.0,"secretaria":9.0,"Cultura":24.0,"Edna":4.0,"Vega":2.0,"subsecretaria":3.0,"TERRITORIAL":1.0,"AGRARIO":4.0,"informe":19.0,"doctor":3.0,"Jorge":1.0,"Hugo":4.0,"Gatell":4.0,"maestro":2.0,"VARELA":1.0,"informará":1.0,"IMSS":26.0,"Bienestar":18.0,"hablará":1.0,"entidades":8.0,"adquisición":8.0,"integración":5.0,"abasto":21.0,"medicamentos":3.0,"tratará":1.0,"ámbito":3.0,"adicciones":8.0,"ABURTO":1.0,"Instituto":9.0,"Informamos":1.0,"institución":2.0,"otorga":3.0,"médica":7.0,"cirugías":2.0,"gratuita":4.0,"asociadas":1.0,"incremento":5.0,"productividad":2.0,"intervenidas":1.0,"iniciamos":1.0,"firmado":1.0,"transferir":1.0,"opera":1.0,"modelo":9.0,"invertido":4.0,"pesos":99.0,"rehabilitación":5.0,"adecuación":7.0,"incluye":5.0,"pisos":1.0,"plafones":1.0,"puertas":4.0,"baños":1.0,"bardas":1.0,"perimetrales":1.0,"ventanas":1.0,"cancelerías":1.0,"eléctricas":1.0,"cárcamos":1.0,"pozos":9.0,"ampliaciones":1.0,"áreas":5.0,"farmacia":1.0,"patio":1.0,"maniobra":1.0,"intervenciones":3.0,"operativas":1.0,"llevaban":4.0,"atendidas":1.0,"adquirido":2.0,"monto":6.0,"tomógrafos":1.0,"rayos":1.0,"X":2.0,"resonancias":1.0,"magnéticas":1.0,"instalen":1.0,"insumos":1.0,"mejore":2.0,"sumado":5.0,"bolsillo":1.0,"pagar":4.0,"especialidad":2.0,"inexistente":1.0,"partos":1.0,"distribuyen":2.0,"Nayarit":4.0,"reporta":7.0,"recetas":1.0,"Colima":2.0,"médicasespecialistas":1.0,"intervenido":2.0,"urgencias":1.0,"inhabilitadas":1.0,"hospitalarias":1.0,"Sonora":10.0,"médicosespecialistas":2.0,"suma":4.0,"reportándose":2.0,"reportado":3.0,"Veracruz":7.0,"comunitarios":2.0,"apartadas":1.0,"comprados":1.0,"muchas":24.0,"especialidades":1.0,"atendiendo":5.0,"destacarlo":1.0,"otorgado":1.0,"empezando":1.0,"trata":3.0,"Hidalgo":6.0,"enviado":4.0,"acabamos":1.0,"echar":2.0,"andar":3.0,"Metztitlán":1.0,"Luis":2.0,"Potosí":5.0,"Tamaulipas":14.0,"destacada":1.0,"puesta":2.0,"marcha":3.0,"oncológico":1.0,"pasada":1.0,"reportero":5.0,"David":1.0,"Pérez":1.0,"Audiorama":1.0,"preguntó":1.0,"licitación":4.0,"contratación":1.0,"anestesia":1.0,"poniendo":1.0,"disposición":1.0,"Coordinación":2.0,"comunicación":15.0,"Presidencia":8.0,"relacionada":1.0,"atentos":1.0,"cualquier":4.0,"duda":3.0,"aclaración":3.0,"SUBSECRETARIO":1.0,"PROMOCIÓN":1.0,"colegas":2.0,"breves":1.0,"culturales":7.0,"genérica":1.0,"conjunto":3.0,"deportivas":2.0,"cultuales":1.0,"recreativas":2.0,"practican":1.0,"cumplido":7.0,"obligaciones":1.0,"laborales":1.0,"escolares":1.0,"familiares":6.0,"destacar":4.0,"elegir":1.0,"individual":2.0,"favorable":3.0,"distribuye":1.0,"desigual":1.0,"desfavoreciendo":1.0,"pobres":4.0,"implantado":1.0,"comentaré":1.0,"centrales":1.0,"Inegi":8.0,"electrónicos":4.0,"divulgación":1.0,"existen":7.0,"sicosociales":1.0,"representar":1.0,"riesgo":5.0,"constituyen":1.0,"estímulo":1.0,"semejante":1.0,"cerebrales":1.0,"cargo":5.0,"Secretaría":39.0,"agradecemos":3.0,"directora":2.0,"Esther":1.0,"Hernández":1.0,"transformador":1.0,"privilegio":3.0,"incorporar":1.0,"verdadera":1.0,"revolución":2.0,"estimular":1.0,"riqueza":8.0,"ponerlo":1.0,"juventud":2.0,"expresen":1.0,"sentimientos":3.0,"personalidad":1.0,"desarrollando":1.0,"Creativo":2.0,"literalmente":1.0,"toma":4.0,"videíto":1.0,"INICIA":5.0,"VIDEO":14.0,"reúnen":1.0,"horas":1.0,"diarias":1.0,"explorar":1.0,"danza":1.0,"circo":1.0,"grafiti":1.0,"fotografía":3.0,"lenguajes":1.0,"expresiones":1.0,"entender":3.0,"incidir":1.0,"realidades":1.0,"NIÑA":8.0,"liberas":1.0,"sientes":1.0,"liberan":1.0,"pintando":1.0,"dibujando":1.0,"cantando":1.0,"bailando":1.0,"mera":1.0,"niñez":1.0,"imaginar":1.0,"capaces":1.0,"transformar":1.0,"cambiado":2.0,"importa":6.0,"digan":1.0,"juzgan":1.0,"siento":2.0,"feliz":5.0,"jugar":1.0,"encuentro":5.0,"colectivo":1.0,"diálogo":2.0,"asambleas":1.0,"artística":2.0,"exploran":1.0,"colectiva":2.0,"forman":1.0,"lazos":1.0,"solidarios":2.0,"involucran":1.0,"diversas":3.0,"imaginan":1.0,"soluciones":1.0,"pacíficas":2.0,"conflictos":1.0,"interesen":1.0,"creen":8.0,"sociedad":3.0,"rompiendo":1.0,"feminicidios":1.0,"machismo":1.0,"homofobia":1.0,"guerras":1.0,"acaban":1.0,"decirle":2.0,"arte":10.0,"pérdida":1.0,"expresión":3.0,"pegamento":1.0,"volver":3.0,"unir":1.0,"quebrada":1.0,"aburrida":1.0,"abuela":1.0,"dijo":18.0,"Mira":1.0,"comenzó":3.0,"felicidad":2.0,"enseñan":2.0,"sabía":2.0,"confianza":6.0,"representan":2.0,"alternativa":1.0,"abandono":1.0,"soledad":1.0,"aislamiento":1.0,"solidarias":1.0,"factores":1.0,"protectores":1.0,"motivan":1.0,"sustancias":1.0,"crecer":1.0,"mágico":1.0,"segura":1.0,"cómoda":1.0,"paz":14.0,"refrescante":1.0,"tocar":1.0,"despejarme":1.0,"niño":4.0,"distraernos":1.0,"transformarnos":1.0,"sensibilizado":1.0,"corazones":1.0,"dóciles":1.0,"Semillero":1.0,"invitación":7.0,"integres":1.0,"des":5.0,"puedes":3.0,"experimentar":1.0,"descubrir":1.0,"ambiente":1.0,"pacífico":2.0,"alegre":2.0,"emociones":1.0,"colectividad":1.0,"dispuesta":1.0,"cobijarte":1.0,"esperes":1.0,"súmate":1.0,"FINALIZA":5.0,"ELENA":1.0,"RANGEL":1.0,"URBANO":1.0,"SEDATU":2.0,"recuerdo":2.0,"constituyó":1.0,"Comisión":2.0,"conformada":1.0,"concluidas":9.0,"plano":3.0,"ven":14.0,"efectivamente":1.0,"daños":8.0,"sismo":8.0,"lámina":2.0,"reconstruido":2.0,"representa":2.0,"beneficiar":3.0,"alumnos":4.0,"indirectos":3.0,"resto":3.0,"imágenes":2.0,"edificaciones":4.0,"secundaria":6.0,"Torres":2.0,"Bodet":1.0,"Nezahualcóyotl":1.0,"Múltiple":2.0,"Jilotzingo":1.0,"otorgar":1.0,"mobiliario":2.0,"requieren":2.0,"totalmente":5.0,"dañado":4.0,"reconstruidas":1.0,"Taxco":2.0,"Alarcón":1.0,"Tepalcingo":1.0,"equipadas":1.0,"especializado":2.0,"Atlixco":1.0,"magnitud":1.0,"Coapa":1.0,"Zacatepec":1.0,"superior":2.0,"patrimonial":6.0,"términos":1.0,"directo":2.0,"porcentaje":5.0,"destinado":3.0,"universo":3.0,"convenio":3.0,"colaboración":3.0,"rescate":2.0,"Dionisio":1.0,"Mar":1.0,"Juchitán":1.0,"Pedro":2.0,"Tapanatepec":1.0,"señalar":1.0,"subsidio":5.0,"administran":2.0,"asesoría":3.0,"técnica":4.0,"tradicional":3.0,"construido":7.0,"Iguala":1.0,"Izúcar":1.0,"Matamoros":4.0,"muestro":1.0,"comentaba":3.0,"Malinaltepec":1.0,"Tochimilco":1.0,"ganó":1.0,"Premio":1.0,"intentando":1.0,"adobe":1.0,"querido":4.0,"sostener":1.0,"conformado":1.0,"Dirección":7.0,"Sitios":4.0,"Monumentos":4.0,"cierre":1.0,"Teatro":1.0,"Juárez":7.0,"detalle":1.0,"concluye":1.0,"cuántas":5.0,"desarrollarán":1.0,"publicaron":6.0,"recientemente":5.0,"reglas":2.0,"apenas":5.0,"iniciaran":1.0,"incluyen":1.0,"iniciadas":2.0,"iniciaron":1.0,"compuesto":1.0,"proyectadas":1.0,"cercana":1.0,"acumulado":1.0,"insistir":2.0,"conclusión":2.0,"compartir":1.0,"edificado":1.0,"potencia":1.0,"queridas":1.0,"Gabinete":1.0,"Roberto":1.0,"Salcedo":1.0,"acompañar":3.0,"ejercicio":4.0,"catástrofe":1.0,"registro":1.0,"república":3.0,"trecho":1.0,"entregado":7.0,"llevando":11.0,"invirtiendo":5.0,"recuperación":3.0,"lineamientos":1.0,"generales":3.0,"trabajemos":1.0,"agilidad":1.0,"interviene":1.0,"Antropología":2.0,"Bellas":2.0,"artístico":2.0,"siglo":1.0,"XX":1.0,"coordinando":1.0,"constante":3.0,"etapa":6.0,"arquitectura":1.0,"vernácula":1.0,"mano":10.0,"agradecimiento":1.0,"paciencia":1.0,"involucrarse":1.0,"xuanas":1.0,"mayordomas":1.0,"mayordomos":1.0,"autoridades":6.0,"religiosas":2.0,"rápida":1.0,"inmueble":31.0,"nunca":27.0,"demoler":1.0,"equiparables":1.0,"originalmente":1.0,"sagrados":1.0,"previas":1.0,"tradicionales":5.0,"subsecretaría":1.0,"reconstruye":1.0,"cero":3.0,"escuela":4.0,"reconstruirlos":1.0,"expertas":1.0,"locales":5.0,"informando":1.0,"tardado":1.0,"singular":1.0,"documentando":1.0,"hazaña":1.0,"Quizá":1.0,"restaurarían":1.0,"plumazo":1.0,"atenderse":1.0,"rápido":1.0,"hablarán":1.0,"ejecutando":2.0,"directa":10.0,"Santa":5.0,"Ocuilan":1.0,"cuidadoso":1.0,"delicado":1.0,"volviera":1.0,"vivo":3.0,"garantiza":1.0,"vuelva":1.0,"debiera":1.0,"Convento":2.0,"Santo":1.0,"Desierto":1.0,"Tenancingo":2.0,"restaurado":6.0,"faldas":1.0,"volcán":3.0,"serie":2.0,"considerados":1.0,"humanidad":2.0,"concluido":6.0,"llamado":1.0,"Cortés":1.0,"Museo":3.0,"murales":2.0,"histórico":8.0,"conocen":1.0,"cerrado":1.0,"abierto":3.0,"destacamos":1.0,"Natividad":1.0,"Tepoztlán":2.0,"cierto":6.0,"ápice":1.0,"altar":1.0,"chimalli":1.0,"indígenas":2.0,"construyeron":1.0,"fe":1.0,"fiestas":3.0,"vuelvan":1.0,"suelen":1.0,"aquello":1.0,"central":1.0,"veneración":1.0,"vitrales":1.0,"supuesto":12.0,"frescos":1.0,"sufrió":2.0,"recuperando":1.0,"campanas":3.0,"esculturas":3.0,"fragmentos":1.0,"retablo":5.0,"reconocimiento":3.0,"capacidades":1.0,"restauradoras":1.0,"capacitado":1.0,"Ana":1.0,"Zegache":1.0,"expediente":2.0,"podamos":1.0,"Imagínense":11.0,"sabrán":1.0,"cuidarlo":1.0,"posterior":1.0,"XVII":1.0,"XVIII":1.0,"trabajan":1.0,"destrucción":1.0,"manual":1.0,"quedará":1.0,"emergencia":7.0,"terminará":1.0,"contundente":1.0,"registraron":2.0,"alcaldías":1.0,"restaurándose":1.0,"monumentales":1.0,"catedral":5.0,"Metropolitana":1.0,"ícono":1.0,"simbólico":1.0,"religioso":5.0,"encontraba":1.0,"bóvedas":3.0,"mural":1.0,"acervo":2.0,"escultórico":1.0,"propiamente":1.0,"ocasionados":1.0,"vegetación":1.0,"incrustado":1.0,"techos":3.0,"amenazaba":1.0,"abrirlos":1.0,"terribles":1.0,"quitó":1.0,"temor":1.0,"pareciera":3.0,"polvorón":1.0,"comentó":3.0,"escuchan":3.0,"tocaban":1.0,"Panteón":1.0,"Fernando":1.0,"Benemérito":1.0,"restauramos":1.0,"osarios":1.0,"funerarios":1.0,"Pongo":1.0,"significativos":3.0,"Quedaron":2.0,"pendientes":4.0,"completamente":4.0,"abandonada":1.0,"cerraron":1.0,"peligroso":1.0,"asistir":6.0,"templo":15.0,"Domingo":1.0,"severamente":1.0,"restauraron":2.0,"altares":2.0,"cubiertas":1.0,"disfrute":3.0,"extranjeros":2.0,"PINEDA":1.0,"ejercido":3.0,"destacan":3.0,"trascendencia":1.0,"legado":4.0,"parroquial":1.0,"Asís":1.0,"Olinalá":1.0,"hermosa":1.0,"Montaña":1.0,"parroquia":1.0,"Prisca":1.0,"símbolo":1.0,"colonial":1.0,"obligada":3.0,"barroco":1.0,"novohispano":1.0,"contrafuertes":2.0,"resguardan":1.0,"final":2.0,"conjunta":4.0,"consolidar":2.0,"campanario":2.0,"Adicionalmente":1.0,"Vientos":1.0,"Acapulco":1.0,"hogar":1.0,"muralista":1.0,"incalculable":1.0,"tradición":2.0,"CRUZ":1.0,"afectaron":1.0,"incorporan":1.0,"municipales":3.0,"afectadas":1.0,"aún":6.0,"contamos":3.0,"concluiremos":1.0,"Guzmán":1.0,"tierra":6.0,"inmortal":1.0,"Sandunga":1.0,"Coixtlahuaca":1.0,"Mixteca":1.0,"Alta":2.0,"prodigio":1.0,"consolidó":1.0,"resarcieron":1.0,"hermosísima":1.0,"capilla":1.0,"abierta":2.0,"atendieron":1.0,"oaxaqueño":3.0,"orgulloso":1.0,"raíces":3.0,"afromexicanas":1.0,"PEREGRINA":1.0,"poblanos":2.0,"permita":1.0,"dirigirnos":1.0,"tribuna":1.0,"ciudadano":3.0,"respaldo":2.0,"solidaridad":3.0,"Saludo":1.0,"esfuerzo":1.0,"derivados":1.0,"preciso":1.0,"comentar":3.0,"ejerceremos":1.0,"disponibles":1.0,"hago":8.0,"mención":3.0,"Gabriel":1.0,"milenario":1.0,"Cholula":1.0,"grietas":1.0,"fisuras":1.0,"Calvario":1.0,"recinto":1.0,"concurrido":1.0,"valorado":1.0,"Petlalcingo":1.0,"fracturas":1.0,"desprendimientos":1.0,"labor":4.0,"demuestra":2.0,"conservar":1.0,"generaciones":2.0,"origen":5.0,"CISNEROS":1.0,"profundamente":1.0,"agradecidos":1.0,"brindado":2.0,"Iglesia":2.0,"Ocotlán":1.0,"Mundial":4.0,"rescatan":1.0,"arquitectónico":2.0,"quede":5.0,"finalizada":1.0,"restantes":1.0,"acto":1.0,"justicia":16.0,"fortalecer":5.0,"identidad":2.0,"difunde":1.0,"donación":1.0,"tren":7.0,"tlaxcalteca":2.0,"convertidas":1.0,"licenciaturas":1.0,"visuales":1.0,"musical":1.0,"vive":2.0,"inscripción":3.0,"conventual":1.0,"franciscano":1.0,"Unesco":1.0,"Rehabilitamos":1.0,"recuperamos":2.0,"colección":1.0,"Frida":1.0,"Kahlo":1.0,"invaluable":1.0,"extraordinaria":1.0,"abrir":3.0,"preguntas":3.0,"Noble":1.0,"presentarnos":1.0,"ingreso":16.0,"vulnerables":1.0,"prioritarios":1.0,"llaman":1.0,"mencionaba":1.0,"viven":1.0,"conocimiento":1.0,"resarcido":1.0,"intención":2.0,"migrar":2.0,"interior":11.0,"demostró":1.0,"alcanzar":1.0,"atiende":1.0,"necesitados":3.0,"neoporfirista":3.0,"aplicaba":1.0,"destinaban":1.0,"orientaban":1.0,"significó":1.0,"décadas":7.0,"corporaciones":3.0,"empresas":3.0,"fiscal":2.0,"engañaban":1.0,"sofismas":1.0,"llovía":1.0,"goteaba":1.0,"contagiosa":1.0,"permeable":1.0,"usual":1.0,"debía":2.0,"intervenir":1.0,"procurar":1.0,"dejarse":1.0,"apostaban":1.0,"incumpliera":1.0,"responsabilidad":2.0,"cambió":1.0,"decidimos":2.0,"comenzamos":1.0,"puso":2.0,"prueba":1.0,"cayó":3.0,"propusieron":1.0,"empresariales":2.0,"regresáramos":1.0,"apoyar":3.0,"contratáramos":1.0,"decretara":1.0,"prórroga":1.0,"representantes":1.0,"recaudar":1.0,"hicimos":2.0,"destinó":1.0,"creara":2.0,"básico":6.0,"continuamos":1.0,"reforzamos":1.0,"destinamos":1.0,"funcionó":2.0,"decirlo":4.0,"ayudaron":1.0,"migrantes":20.0,"necesitábamos":1.0,"incrementaron":1.0,"remesas":1.0,"apartados":1.0,"ayudó":4.0,"iniciado":1.0,"incrementó":1.0,"idea":2.0,"Peña":1.0,"Nieto":1.0,"billón":1.0,"doble":2.0,"fortaleció":1.0,"pronto":1.0,"creciendo":6.0,"moral":3.0,"Humanismo":1.0,"dije":6.0,"patentarlo":1.0,"imponen":1.0,"países":29.0,"causan":1.0,"desgracias":1.0,"reducir":7.0,"caemos":1.0,"adversarios":5.0,"salen":4.0,"reducción":11.0,"comparamos":1.0,"obtenían":1.0,"decil":2.0,"recibían":1.0,"subrayo":1.0,"plena":2.0,"caída":1.0,"brecha":1.0,"reciben":1.0,"necesariamente":1.0,"empobreciendo":1.0,"probar":1.0,"único":8.0,"campesino":1.0,"choco":1.0,"jarocho":1.0,"milpa":1.0,"alcanza":1.0,"pájaro":1.0,"satisfactorio":1.0,"necesitamos":5.0,"escuchar":2.0,"necesitada":1.0,"benefician":2.0,"clase":6.0,"media":1.0,"beneficia":2.0,"comercio":2.0,"recomendación":3.0,"magonistas":1.0,"Liberal":2.0,"planes":3.0,"agregaría":1.0,"debemos":1.0,"pones":5.0,"frasean":1.0,"esencia":1.0,"sexenal":1.0,"inicio":2.0,"Cárdenas":5.0,"recomiendo":1.0,"añadido":1.0,"presentamos":1.0,"Saben":2.0,"siguiendo":1.0,"pautas":1.0,"recomendaciones":2.0,"apegado":1.0,"imponían":2.0,"llamadas":1.0,"estructurales":1.0,"agenda":5.0,"miren":2.0,"parias":1.0,"vegetan":1.0,"hambre":1.0,"desnudez":1.0,"coman":1.0,"usen":1.0,"ropa":3.0,"calzado":1.0,"dejen":1.0,"petate":1.0,"ajuar":1.0,"demanda":4.0,"géneros":1.0,"objetos":1.0,"insignificante":1.0,"aumentará":1.0,"proporciones":1.0,"colosales":1.0,"agricultura":1.0,"materialmente":1.0,"empujado":1.0,"desarrollarse":1.0,"escala":1.0,"jamás":1.0,"alcanzaría":1.0,"subsistieran":1.0,"actuales":1.0,"miseria":1.0,"clave":1.0,"esencial":1.0,"considera":2.0,"contribuir":5.0,"migren":1.0,"menciona":1.0,"obligación":1.0,"puro":1.0,"placer":1.0,"beneficiando":1.0,"intentona":1.0,"migración":14.0,"abandonaron":1.0,"buscaron":5.0,"sureste":8.0,"isla":1.0,"Riviera":1.0,"Hablo":1.0,"Norte":9.0,"agradecerle":2.0,"yucatecos":1.0,"campechanos":1.0,"chiapanecos":1.0,"guerrerenses":1.0,"buscarse":1.0,"decrecimiento":1.0,"crecía":1.0,"veracruzanos":2.0,"Reynosa":1.0,"turísticos":1.0,"Vallarta":1.0,"conurbada":1.0,"Huasteca":2.0,"potosina":1.0,"horizontal":2.0,"grado":2.0,"perdió":1.0,"despoblaron":1.0,"concentró":1.0,"oportunidades":1.0,"crecieron":1.0,"beneficiaron":1.0,"creció":6.0,"decreció":1.0,"parejura":1.0,"regresando":2.0,"espero":2.0,"pláticas":1.0,"trabajador":2.0,"vámonos":3.0,"regreso":1.0,"posibilidades":3.0,"recibir":4.0,"pensión":3.0,"aumentar":1.0,"suficiente":3.0,"regresar":2.0,"vivir":1.0,"pierden":3.0,"querencia":1.0,"Imaginemos":1.0,"nacionalidad":1.0,"observa":1.0,"envían":1.0,"ayudando":6.0,"vea":2.0,"emigrar":2.0,"tercer":2.0,"desempleo":2.0,"tasa":1.0,"aumenten":1.0,"fácil":1.0,"obreros":1.0,"calificados":1.0,"fierreros":1.0,"soldadores":1.0,"difícil":2.0,"operadores":1.0,"entregue":3.0,"bastón":4.0,"mando":4.0,"entrego":1.0,"quedo":1.0,"terminando":1.0,"esbozo":1.0,"deje":1.0,"invertir":1.0,"pare":1.0,"reactiva":1.0,"produce":5.0,"montar":1.0,"bicicleta":1.0,"pedalear":1.0,"terminó":4.0,"Coatzacoalcos":1.0,"Yluego":1.0,"Ypor":1.0,"pasajeros":5.0,"carga":1.0,"generan":1.0,"carreteras":3.0,"energético":1.0,"pensando":6.0,"refinería":1.0,"energías":1.0,"renovables":1.0,"empezar":6.0,"rehabilitar":1.0,"petroquímica":1.0,"quebraron":1.0,"destruyeron":1.0,"ruina":1.0,"neoliberales":3.0,"analistas":1.0,"economistas":1.0,"Wall":1.0,"Street":1.0,"Shanghái":1.0,"piensan":3.0,"empiece":1.0,"funcionar":1.0,"Corredor":1.0,"actualidad":1.0,"factible":2.0,"acelere":1.0,"proyectos":3.0,"reacomodos":1.0,"inversionistas":1.0,"dispuestos":1.0,"integrar":1.0,"depender":2.0,"Asia":5.0,"moviendo":1.0,"semestre":1.0,"socio":1.0,"comercial":3.0,"llegando":6.0,"extranjera":1.0,"coincidimos":1.0,"complementamos":2.0,"echó":1.0,"Fíjense":1.0,"cuarto":3.0,"ventaja":1.0,"fronteriza":3.0,"aplicado":1.0,"pagan":2.0,"impuesto":1.0,"renta":3.0,"aumentó":1.0,"foránea":1.0,"proponiendo":1.0,"busque":1.0,"continente":3.0,"americano":1.0,"insistiendo":5.0,"planeación":1.0,"mediano":3.0,"plazo":3.0,"Biden":17.0,"noviembre":7.0,"invitó":1.0,"bilateral":1.0,"coincide":1.0,"fortalecimiento":1.0,"mecanismos":1.0,"financiamiento":4.0,"accesible":1.0,"créditos":3.0,"planteando":3.0,"Alianza":3.0,"Kennedy":4.0,"fenómeno":5.0,"migratorio":7.0,"violencia":17.0,"preocupa":1.0,"demostrado":1.0,"lograr":6.0,"excluir":1.0,"aquel":2.0,"ideológicas":1.0,"incluyó":2.0,"propuesta":6.0,"Cuba":1.0,"participen":1.0,"participemos":1.0,"convierte":1.0,"auge":1.0,"Europa":3.0,"Europea":2.0,"Unión":1.0,"garantías":1.0,"felices":1.0,"virtual":1.0,"presencial":1.0,"reunirse":1.0,"homólogo":3.0,"Colombia":8.0,"platicar":2.0,"drogas":1.0,"adelantar":2.0,"tratar":3.0,"cooperación":1.0,"naciones":3.0,"cese":1.0,"narcotráfico":1.0,"compartirles":1.0,"experiencia":5.0,"especie":1.0,"copia":1.0,"acreditar":1.0,"atienden":1.0,"aminorar":1.0,"fruto":3.0,"arraigue":1.0,"conductas":1.0,"antisociales":1.0,"enganchen":3.0,"conviertan":1.0,"delincuentes":2.0,"concientización":1.0,"material":2.0,"lujo":1.0,"barato":2.0,"consumismo":1.0,"morales":2.0,"espirituales":1.0,"corriente":1.0,"individualista":2.0,"triunfar":1.0,"escrúpulos":1.0,"índole":1.0,"estafando":1.0,"ponen":2.0,"pagaban":5.0,"traer":2.0,"película":1.0,"Cantinflas":1.0,"elegante":1.0,"damas":1.0,"camina":1.0,"voltea":1.0,"camisa":1.0,"hacerles":3.0,"publicidad":9.0,"Ferrari":1.0,"canción":3.0,"cantante":1.0,"camioneta":2.0,"Mercedes":2.0,"troca":1.0,"relojes":2.0,"apogeo":1.0,"contratista":1.0,"predilecto":1.0,"mandaba":1.0,"pena":1.0,"consumista":1.0,"fomentada":2.0,"estudiando":3.0,"repente":1.0,"alhajas":1.0,"moda":1.0,"haces":1.0,"enseño":1.0,"enganchan":1.0,"humanos":1.0,"problemas":1.0,"plantea":1.0,"Petro":1.0,"respetamos":1.0,"invita":1.0,"conclusiones":1.0,"Amir":1.0,"Ibrahim":1.0,"Mx":1.0,"metido":1.0,"Legislativo":2.0,"utilizando":3.0,"digamos":4.0,"desacreditando":1.0,"versión":2.0,"empiezan":1.0,"utilizado":1.0,"meterse":1.0,"recurren":1.0,"menguando":1.0,"ciudadana":3.0,"contraste":1.0,"pronta":4.0,"expedita":4.0,"ciudadanía":1.0,"durar":1.0,"investigaciones":1.0,"sometida":1.0,"impartición":1.0,"lenta":1.0,"juicio":3.0,"gestar":1.0,"doblar":1.0,"voluntad":2.0,"imponerse":1.0,"popular":1.0,"molestos":2.0,"denuncia":1.0,"jueces":4.0,"magistrados":4.0,"quieren":6.0,"perder":1.0,"violando":5.0,"guardadito":1.0,"otorgando":1.0,"sobresueldos":1.0,"financiando":1.0,"privada":1.0,"cajas":1.0,"domésticos":1.0,"hagan":5.0,"jardinería":1.0,"prebendas":1.0,"conceden":1.0,"escudan":1.0,"chueco":1.0,"cohecho":1.0,"reforma":7.0,"podían":5.0,"llevarla":1.0,"comenzar":1.0,"impongan":1.0,"aparentemente":1.0,"particos":2.0,"maneja":1.0,"Claudio":1.0,"refiero":1.0,"imparta":1.0,"poderoso":1.0,"caballero":1.0,"don":1.0,"liberando":1.0,"deberían":4.0,"inocente":1.0,"sentenciada":1.0,"libros":39.0,"suplir":1.0,"enseñarle":1.0,"impartir":1.0,"promoviendo":3.0,"repartan":1.0,"decidió":2.0,"repartir":2.0,"termine":3.0,"autoriza":1.0,"cuadernillos":2.0,"levanten":1.0,"vincular":1.0,"temporadas":1.0,"desesperados":1.0,"funciona":1.0,"recurrido":1.0,"campañas":1.0,"manipulan":1.0,"ejemplar":1.0,"informa":1.0,"carta":19.0,"opina":3.0,"sabe":7.0,"opino":1.0,"enviar":10.0,"responsable":1.0,"combatir":2.0,"jurídicamente":1.0,"trámite":7.0,"jurídico":1.0,"desaforar":1.0,"amigos":2.0,"formación":1.0,"profesiones":1.0,"recomendarme":1.0,"amparara":1.0,"amparar":3.0,"desaforaban":1.0,"pensado":5.0,"saliera":2.0,"orden":1.0,"aprehensión":1.0,"acercarme":1.0,"reclusorio":2.0,"espectáculo":1.0,"García":1.0,"Luna":1.0,"procuraduría":1.0,"llegué":1.0,"escolta":1.0,"armas":3.0,"foto":1.0,"Martin":1.0,"luchaba":1.0,"civiles":5.0,"metieron":2.0,"manejando":1.0,"exceso":2.0,"velocidad":3.0,"luchador":1.0,"Gandhi":1.0,"Mandela":1.0,"vas":4.0,"vinculada":2.0,"Felipe":1.0,"pagaron":2.0,"fianza":1.0,"dicen":11.0,"publicamos":1.0,"contenidos":2.0,"publíquenlos":1.0,"chicanadas":1.0,"mismoque":1.0,"abogado":3.0,"ganar":2.0,"justas":1.0,"cargados":1.0,"concepción":1.0,"guardar":1.0,"quiera":1.0,"avispado":1.0,"inteligente":1.0,"virus":3.0,"vacunar":5.0,"Oiga":1.0,"adoctrinamiento":1.0,"rindo":1.0,"Siga":1.0,"responsabilidades":1.0,"vísperas":1.0,"clara":2.0,"violar":2.0,"manifiesto":1.0,"atreven":1.0,"violación":1.0,"esquema":1.0,"leguleya":1.0,"percibe":1.0,"violado":1.0,"sucede":1.0,"pudieron":2.0,"hablado":5.0,"Mateos":1.0,"salieron":1.0,"calle":1.0,"organizaciones":1.0,"avanzó":1.0,"entregaran":1.0,"primaria":2.0,"contribuimos":1.0,"promotores":2.0,"Zedillo":3.0,"expliqué":1.0,"utilizar":4.0,"llegaban":1.0,"opusimos":1.0,"electoral":21.0,"cobrando":4.0,"cheque":2.0,"excedente":2.0,"empezaron":1.0,"viudas":1.0,"huérfanos":3.0,"perdido":1.0,"luchando":1.0,"daba":3.0,"becas":5.0,"defender":1.0,"gratuitamente":1.0,"gobernábamos":1.0,"pusieron":1.0,"enojadísimos":1.0,"Limón":1.0,"polémica":2.0,"hemeroteca":1.0,"ataques":1.0,"populismo":1.0,"entregamos":3.0,"gratuitos":5.0,"cobraban":3.0,"editoriales":1.0,"circular":2.0,"mensajes":1.0,"ida":1.0,"vuelta":5.0,"periodísticas":1.0,"facturas":1.0,"cuánto":7.0,"ventile":1.0,"enojarse":2.0,"venga":1.0,"concede":1.0,"suspensión":1.0,"podríamos":3.0,"ventilar":1.0,"manejaba":1.0,"oscurito":1.0,"debate":1.0,"purificando":1.0,"recordando":1.0,"Pemex":3.0,"votaban":1.0,"opuso":2.0,"surgió":1.0,"sabían":5.0,"votando":3.0,"Ejidatarios":1.0,"reparto":1.0,"ejido":1.0,"alguien":3.0,"auténticamente":1.0,"demócratas":1.0,"pluralidad":1.0,"pensamiento":2.0,"sometidos":1.0,"subordinados":1.0,"libertades":1.0,"censurado":1.0,"rapidísimo":2.0,"aprovechando":2.0,"Pedrero":1.0,"Erick":1.0,"Línea":1.0,"Jacobo":1.0,"Elnecavé":1.0,"Redes":1.0,"Vicente":5.0,"Serrano":3.0,"tianguis":4.0,"Chopo":3.0,"manifestaron":1.0,"representativo":1.0,"rebelde":1.0,"digámoslo":1.0,"nombrar":1.0,"concordancia":1.0,"vimos":1.0,"solicitarle":3.0,"estatus":1.0,"Vocería":1.0,"estilo":3.0,"seguimiento":1.0,"publicaciones":1.0,"alternativo":1.0,"novedosas":1.0,"Pantoja":1.0,"trabajado":1.0,"parece":1.0,"veríamos":1.0,"alentar":1.0,"ojos":1.0,"contacto":1.0,"platicamos":1.0,"inmediatamente":1.0,"recogemos":1.0,"planteamiento":1.0,"Arturo":1.0,"Páramo":4.0,"Imagen":7.0,"recibe":2.0,"merece":3.0,"solicitud":3.0,"contempla":1.0,"prerrogativas":3.0,"Veintitrés":1.0,"Setecientos":1.0,"cincuenta":1.0,"incluido":1.0,"Aparte":3.0,"costosas":1.0,"investigar":3.0,"mirones":1.0,"VOCERO":5.0,"Diez":2.0,"tarea":12.0,"mañana":14.0,"comparativo":3.0,"informemos":1.0,"gasta":8.0,"Francia":3.0,"Japón":3.0,"Brasil":3.0,"Rica":3.0,"toca":2.0,"sorteo":1.0,"realiza":1.0,"cuestan":2.0,"contestar":5.0,"aceptamos":1.0,"integramos":1.0,"tocarlo":1.0,"envía":4.0,"Congreso":3.0,"publica":1.0,"criterios":1.0,"cálculo":1.0,"estimación":3.0,"manejarse":1.0,"modificar":1.0,"manda":5.0,"exclusiva":1.0,"Cámara":3.0,"Diputados":3.0,"aprobar":1.0,"enviamos":1.0,"previsión":1.0,"Pásale":1.0,"nota":37.0,"digas":1.0,"apoblación":1.0,"voto":3.0,"UNAM":1.0,"convocatoria":3.0,"selección":1.0,"ocupar":1.0,"rectoría":1.0,"autónoma":1.0,"universidad":1.0,"resolverlo":2.0,"universitarios":2.0,"lanzando":1.0,"conformidad":1.0,"marco":3.0,"vigente":5.0,"adelantando":1.0,"opinar":1.0,"cuestión":1.0,"deseo":1.0,"honestidad":3.0,"autonomía":2.0,"estricto":1.0,"cacicazgos":1.0,"deba":1.0,"caciques":1.0,"duran":1.0,"MARTÍ BATRES":3.0,"Evelyn Salgado":3.0,"Lorena Cuéllar":3.0,"Salomón Jara":2.0,"Rutilio Escandón":2.0,"Escandón Cadenas":2.0,"Sergio Salomón":2.0,"Salomón Céspedes":2.0,"Alejandra Frausto":3.0,"Ordenamiento Territorial":2.0,"Jorge Alcocer":2.0,"maestro Zoé":3.0,"Zoé Robledo":3.0,"IMSS Bienestar":5.0,"seguridad social":3.0,"equipos médicos":10.0,"médicos especialistas":9.0,"medicina familiar":2.0,"sumado médicos":6.0,"inversión total":9.0,"recetas surtidas":2.0,"Baja California":5.0,"equipo médico":6.0,"sumado médicas":4.0,"Quintana Roo":9.0,"tiempo libre":4.0,"Semilleros Creativos":8.0,"propias comunidades":3.0,"VOZ MUJER":5.0,"Programa Nacional":6.0,"empleos directos":3.0,"patrimonio cultural":8.0,"Benito Juárez":2.0,"Instituto Nacional":4.0,"gobiernos estatales":4.0,"siglo XVI":2.0,"Diego Rivera":2.0,"bienes muebles":5.0,"BATRES GUADARRAMA":2.0,"Santo Domingo":3.0,"visitantes nacionales":2.0,"sufrieron afectaciones":2.0,"San Francisco":10.0,"arquitectura virreinal":3.0,"Antiguo Convento":2.0,"política económica":3.0,"pagaran impuestos":2.0,"inversión pública":5.0,"organismos financieros":2.0,"financieros internacionales":2.0,"periodo neoliberal":4.0,"producto interno":2.0,"interno bruto":2.0,"salario mínimo":7.0,"Luther King":2.0,"dejan manipular":2.0,"trabajadores petroleros":2.0,"expropiación petrolera":2.0,"recolectando firmas":2.0,"miércoles":2.0,"sección":4.0,"semana'":4.0,"abrimos":2.0,"Elizabeth":8.0,"ANA":4.0,"GARCÍA":2.0,"iniciar":6.0,"ataca":2.0,"dedicó":2.0,"planas":2.0,"ataque":4.0,"Seguro":6.0,"columnas":6.0,"fantasma":6.0,"resultó":2.0,"falso":12.0,"aclaró":4.0,"Aristegui":4.0,"Noticias":10.0,"Vanguardia":2.0,"AM":2.0,"Mural":2.0,"PM":2.0,"Soluciones":2.0,"C":2.0,"V":2.0,"distintos":6.0,"únicamente":4.0,"mantiene":2.0,"contractual":2.0,"aviso":2.0,"modificación":2.0,"domicilio":8.0,"Infonavit":2.0,"efectos":2.0,"1º":2.0,"tendenciosa":2.0,"supuesta":2.0,"cita":2.0,"informante":2.0,"Favor":4.0,"afirma":4.0,"dependencias":2.0,"contratos":10.0,"asignación":2.0,"miente":2.0,"afirmado":2.0,"reportaje":4.0,"aplica":2.0,"registrada":2.0,"contratadas":2.0,"figuran":2.0,"Registro":4.0,"Comercio":4.0,"contándole":2.0,"mencionados":2.0,"adjudicación":4.0,"concurso":2.0,"inventa":2.0,"Auditoría":4.0,"Superior":2.0,"Federación":2.0,"escuchen":4.0,"afirmó":2.0,"informáticos":2.0,"mencionan":2.0,"softwares":2.0,"señaló":2.0,"aparente":2.0,"duplicidad":2.0,"contrataciones":2.0,"control":4.0,"interno":2.0,"ahorrar":2.0,"prestación":2.0,"contratado":6.0,"cabe":2.0,"actualizar":2.0,"avanzar":4.0,"digitalización":2.0,"desmentido":2.0,"comentaristas":8.0,"minimizaron":4.0,"logro":6.0,"radio":6.0,"televisión":2.0,"difunden":2.0,"minimizan":2.0,"buenas":4.0,"avances":2.0,"económicos":2.0,"reporte":10.0,"Coneval":18.0,"familias":4.0,"levantado":2.0,"honra":2.0,"cuarta":12.0,"debido":6.0,"decimos":2.0,"gubernamental":2.0,"destacando":4.0,"Benito":2.0,"minimizó":2.0,"Veamos":8.0,"pantalla":6.0,"Siendo":4.0,"digitales":2.0,"superando":2.0,"Amplio":4.0,"seguido":2.0,"sesgo":4.0,"informativo":4.0,"cree":2.0,"siguieron":2.0,"coordinar":8.0,"Defensa":24.0,"4T":4.0,"Dicho":10.0,"difundidas":2.0,"grueso":2.0,"mintieron":2.0,"acceso":16.0,"gráfica":20.0,"mandaron":2.0,"cuantitativo":2.0,"tratamiento":2.0,"portadas":2.0,"vean":2.0,"Universal":2.0,"Financiero":2.0,"Economista":2.0,"Excélsior":2.0,"Sol":2.0,"Horas":2.0,"Crónica":4.0,"Publimetro":2.0,"minimizando":2.0,"desmentir":2.0,"Animal":2.0,"Proceso":4.0,"Sergio":2.0,"Sarmiento":2.0,"Javier":2.0,"Tello":2.0,"Gustavo":2.0,"expresidente":4.0,"Fox":2.0,"mensaje":4.0,"agresivo":2.0,"fiel":2.0,"Pascal":2.0,"Beltrán":2.0,"etcétera":2.0,"televisoras":2.0,"tocaron":2.0,"Milenio":4.0,"MVS":2.0,"Fórmula":4.0,"dedican":4.0,"Ecuador":6.0,"vínculo":2.0,"cártel":2.0,"tocan":2.0,"agregan":2.0,"subió":2.0,"N":2.0,"noticiero":2.0,"Punto":2.0,"Enrique":2.0,"Acevedo":2.0,"inseguridad":6.0,"TV":4.0,"Azteca":2.0,"apoderaron":2.0,"oscuros":2.0,"cometidos":2.0,"inocular":2.0,"mencionó":4.0,"disminuyó":4.0,"pospandemia":2.0,"AMLO'":2.0,"extrema":2.0,"midiendo":2.0,"unísono":2.0,"destacaron":6.0,"duplicó":2.0,"engañoso":4.0,"mantuvo":4.0,"dirigida":2.0,"realizada":4.0,"resultaba":2.0,"extemporánea":2.0,"incorrecta":2.0,"juzgar":2.0,"Actualmente":2.0,"afiliado":4.0,"inscrito":4.0,"desaparecido":2.0,"Insabi":4.0,"contó":2.0,"propios":2.0,"administrados":2.0,"Obviamente":2.0,"afiliada":2.0,"contestó":2.0,"cifra":12.0,"respuesta":4.0,"dolor":2.0,"malestar":2.0,"enfermedad":2.0,"accidente":4.0,"recibieron":8.0,"atendidos":2.0,"necesitaron":2.0,"omitieron":2.0,"deliberadamente":2.0,"costumbre":4.0,"ubicó":2.0,"treceavo":2.0,"desfavorecidas":2.0,"continuación":2.0,"larga":2.0,"anteriores":4.0,"verdaderamente":2.0,"indignante":2.0,"vergonzoso":4.0,"gobernaba":2.0,"bajó":4.0,"claramente":2.0,"comparación":6.0,"carencia":8.0,"afuera":2.0,"infodemia":4.0,"aborda":2.0,"publicadas":2.0,"Mexicana":26.0,"Aérea":6.0,"aviones":10.0,"Aviación":16.0,"Tras":2.0,"comenzaría":2.0,"volar":4.0,"aerolínea":20.0,"despegaron":2.0,"Boeing":6.0,"aeronaves":4.0,"tripulación":4.0,"éstas":2.0,"personal":4.0,"certificado":2.0,"operador":2.0,"aéreo":2.0,"elementos":12.0,"implementarse":2.0,"civil":2.0,"afirmaron":2.0,"militar":4.0,"Sedena":4.0,"administrará":2.0,"encargada":2.0,"creado":2.0,"empleos":2.0,"empleará":2.0,"operaciones":2.0,"boletos":6.0,"subsidiados":2.0,"titular":4.0,"informaron":2.0,"costo":12.0,"explicaron":2.0,"deberá":2.0,"actual":2.0,"usuarios":2.0,"afán":2.0,"lucro":2.0,"rutas":4.0,"presentación":2.0,"comenzará":2.0,"AIFA":2.0,"destinos":4.0,"inaugurará":2.0,"prevé":2.0,"volará":2.0,"Dónde":4.0,"hiciste":2.0,"recuento":2.0,"Después":2.0,"comparativa":2.0,"ejerce":4.0,"aparato":2.0,"particularidad":4.0,"permanencia":2.0,"conformando":2.0,"previo":2.0,"permanente":2.0,"electorales":2.0,"somero":2.0,"pude":2.0,"redacciones":2.0,"tomé":2.0,"órgano":4.0,"correspondiente":2.0,"legislativas":2.0,"presidenciales":2.0,"dividió":2.0,"asignado":4.0,"entra":2.0,"específica":2.0,"votación":4.0,"espejo":2.0,"pequeña":2.0,"regímenes":2.0,"parlamentarios":2.0,"despierta":2.0,"copiosas":2.0,"equiparable":4.0,"independiente":4.0,"similar":2.0,"Panamá":2.0,"elector":2.0,"inscrita":2.0,"padrón":2.0,"Costa":4.0,"actualiza":2.0,"diariamente":2.0,"Uruguay":2.0,"Honduras":2.0,"obligatorio":2.0,"voluntario":2.0,"altos":2.0,"obligados":4.0,"Perú":2.0,"Bolivia":2.0,"Nicaragua":2.0,"electores":4.0,"electrónicas":2.0,"utilizan":2.0,"intentará":2.0,"Guatemala":2.0,"Paraguay":2.0,"España":2.0,"euros":4.0,"fresco":2.0,"particularidades":2.0,"rebasa":2.0,"comprensión":2.0,"conocemos":2.0,"India":2.0,"destina":2.0,"Rusia":2.0,"Inglaterra":2.0,"libras":2.0,"emite":2.0,"Mande":2.0,"escuchando":4.0,"Consideraría":2.0,"excesivo":2.0,"ahorrarse":2.0,"destinaría":1.0,"necesitaría":2.0,"bajarlo":2.0,"iniciativa":10.0,"rechazaron":2.0,"plantear":4.0,"Vámonos":6.0,"Nación":8.0,"solicitar":4.0,"deficientes":2.0,"estatales":2.0,"Federal":2.0,"quite":2.0,"meses":6.0,"escasez":2.0,"descubrimos":4.0,"administraciones":2.0,"pasadas":2.0,"estudios":2.0,"impide":2.0,"salir":6.0,"imposibilitados":2.0,"acceder":6.0,"BID":2.0,"coopera":2.0,"coopere":2.0,"acompañe":4.0,"federativas":2.0,"cuenten":2.0,"finanzas":2.0,"sanas":2.0,"desarrollar":2.0,"hidráulicos":2.0,"ayuden":6.0,"padecen":2.0,"abastecer":6.0,"distintas":2.0,"Picacho":4.0,"concluyó":2.0,"acueducto":12.0,"Mazatlán":2.0,"Concordia":2.0,"permitir":12.0,"falte":4.0,"riego":4.0,"Laguna":4.0,"implicación":2.0,"Nueve":6.0,"arsénico":2.0,"superficial":2.0,"represas":2.0,"bombeo":2.0,"potabilizadoras":2.0,"tanques":2.0,"abastecimiento":2.0,"kilómetros":8.0,"tubería":2.0,"Cuchillo":2.0,"II":2.0,"metropolitana":2.0,"Zapotillo":2.0,"Xpujil":2.0,"piense":2.0,"demasiada":2.0,"doméstico":2.0,"escasea":2.0,"hidráulicas":2.0,"terminadas":2.0,"signifique":6.0,"apoya":2.0,"Banobras":2.0,"podrían":2.0,"gestiones":2.0,"obtención":2.0,"extranjero":10.0,"negado":2.0,"garantizando":4.0,"prioritario":2.0,"monitoreando":4.0,"trajimos":2.0,"comiencen":2.0,"malla":4.0,"Realito":2.0,"dueña":2.0,"concesión":4.0,"ducto":8.0,"realizando":4.0,"llovió":2.0,"sirve":2.0,"roto":2.0,"sacando":4.0,"pipas":2.0,"pese":4.0,"Conagua":6.0,"anunció":4.0,"concesionaria":2.0,"aumentando":4.0,"vinieron":2.0,"negó":2.0,"dejándolos":2.0,"banco":12.0,"ocupan":2.0,"estancamiento":2.0,"flujo":4.0,"Germán":2.0,"Martínez":2.0,"daría":4.0,"enteren":2.0,"habló":2.0,"existía":4.0,"damos":4.0,"federales":2.0,"muelle":2.0,"relacionado":2.0,"tocó":2.0,"Altamira":4.0,"licuefacción":4.0,"instalación":2.0,"fertilizantes":2.0,"exgobernador":2.0,"Cabeza":2.0,"Vaca":2.0,"comentarios":2.0,"coordinador":6.0,"Ángel":2.0,"convirtieron":2.0,"hablo":4.0,"sancionar":2.0,"periodista":14.0,"Trinidad":2.0,"Malpica":2.0,"falleció":2.0,"terminaba":2.0,"diría":2.0,"trayectoria":2.0,"periodístico":2.0,"comento":2.0,"Joaquín":2.0,"Dóriga":2.0,"Portillo":2.0,"Félix":2.0,"Galván":6.0,"Ricardo":2.0,"Riva":2.0,"Antonio":2.0,"Riviello":2.0,"Bazán":2.0,"Rafael":4.0,"Cardona":2.0,"Madrid":2.0,"Hurtado":2.0,"Juan":2.0,"Arévalo":2.0,"Gardoqui":2.0,"Guillermo":2.0,"atrevieron":2.0,"criticar":2.0,"ácidamente":4.0,"Ejército":32.0,"consecuencias":2.0,"inmediatas":2.0,"atenían":2.0,"quinto":4.0,"Armadas":2.0,"garantes":4.0,"salvaguardia":2.0,"republicanas":2.0,"criticado":2.0,"nació":2.0,"reflexión":2.0,"gabinete":18.0,"Legal":6.0,"Ampliado":4.0,"almirante":2.0,"Marina":20.0,"Ojeda":2.0,"sostienen":2.0,"apoyado":2.0,"ayudándonos":2.0,"misiones":4.0,"orientadas":2.0,"soberanía":10.0,"independencia":6.0,"misión":24.0,"cabalmente":6.0,"valer":2.0,"apego":2.0,"exterior":4.0,"define":2.0,"soberano":2.0,"colonia":2.0,"asociado":2.0,"protectorados":2.0,"fortalecido":2.0,"cuidan":2.0,"estratégicas":2.0,"Electricidad":4.0,"labores":8.0,"tranquilidad":4.0,"proteger":2.0,"profesionalismo":2.0,"constituye":2.0,"cumpliendo":4.0,"contribuya":2.0,"mejoras":2.0,"Ayudaron":2.0,"dosis":2.0,"vacunas":6.0,"apartado":2.0,"islas":2.0,"enfermeras":2.0,"Hospital":2.0,"excepcional":2.0,"participado":2.0,"construcciones":2.0,"sucursales":2.0,"distritos":2.0,"ayudado":10.0,"desazolve":2.0,"desembocadura":2.0,"marítimos":2.0,"quinta":2.0,"cumplida":2.0,"auxilio":4.0,"Quiénes":2.0,"llegan":2.0,"inundaciones":4.0,"derrumbes":2.0,"actúan":2.0,"erupción":2.0,"emisiones":2.0,"cenizas":2.0,"tormenta":2.0,"sierra":4.0,"Zongolica":2.0,"graves":2.0,"DN":2.0,"III":2.0,"pie":2.0,"motivo":2.0,"difundir":4.0,"orígenes":2.0,"marino":6.0,"soldado":8.0,"uniformado":2.0,"desprestigio":2.0,"Ponlo":2.0,"alquimia":2.0,"perfecta":2.0,"modernidad":2.0,"pertenecemos":2.0,"Fuerza":4.0,"consagramos":2.0,"ofrendarla":2.0,"mantenemos":2.0,"leales":2.0,"dudar":2.0,"darlo":2.0,"Convencidos":2.0,"lealtad":2.0,"defendiendo":4.0,"integridad":2.0,"auxiliando":2.0,"brindando":2.0,"cumplimiento":2.0,"deber":2.0,"contribuyendo":2.0,"realización":2.0,"transformen":2.0,"ofreciendo":2.0,"hermanas":2.0,"precise":2.0,"orgullosos":4.0,"uniforme":2.0,"portamos":2.0,"insignias":2.0,"honran":2.0,"hermanos":4.0,"imprescindible":2.0,"velando":2.0,"salvaguarda":2.0,"sigamos":2.0,"tesoro":2.0,"cercanía":2.0,"convicción":4.0,"motivación":2.0,"estrenamos":2.0,"bonito":2.0,"Faltó":2.0,"calificación":2.0,"motor":2.0,"llamada":2.0,"engañar":2.0,"honestos":2.0,"significado":2.0,"aprendices":2.0,"centros":4.0,"formaron":2.0,"Cuándo":8.0,"Imjuve":2.0,"aprovecho":2.0,"transmitir":2.0,"mecanismo":2.0,"cobro":2.0,"inició":2.0,"dispersión":2.0,"cobrar":2.0,"pilotos":2.0,"significan":2.0,"improvisado":2.0,"notado":2.0,"veía":4.0,"esfuerzos":2.0,"imaginación":2.0,"talento":2.0,"invito":2.0,"hice":4.0,"déjenme":2.0,"presumir":2.0,"actualizado":2.0,"temporada":2.0,"Epigmenio":2.0,"Ibarra":4.0,"estima":2.0,"gigante":4.0,"Lázaro":2.0,"octubre":2.0,"mundial":4.0,"anulado":2.0,"refirió":2.0,"receta":2.0,"globalmente":2.0,"sencilla":2.0,"austeridad":4.0,"impunidad":2.0,"tolerar":2.0,"derrotó":2.0,"dejará":4.0,"zapatos":2.0,"renunciar":2.0,"liderazgo":2.0,"Morena":2.0,"orfandad":2.0,"demostrándose":2.0,"efectividad":2.0,"combinación":2.0,"humanismo":4.0,"austero":2.0,"lujos":4.0,"ahorrado":12.0,"superfluos":2.0,"onerosos":2.0,"derrochar":2.0,"dedicarlo":2.0,"acepte":2.0,"rico":6.0,"ingresa":2.0,"impuestos":6.0,"ahorramos":2.0,"condonación":2.0,"financieras":2.0,"calculo":2.0,"robaban":2.0,"huachicol":2.0,"robo":2.0,"usar":4.0,"privados":4.0,"helicópteros":2.0,"tantos":2.0,"olvidó":2.0,"ídolos":2.0,"cuestionaban":2.0,"avión":12.0,"llenos":2.0,"perico":2.0,"compañera":2.0,"caballo":2.0,"vergüenza":2.0,"cínicos":2.0,"sacaban":2.0,"pon":2.0,"vi":2.0,"anterior":4.0,"masca":2.0,"iguana":2.0,"ladeado":2.0,"interpretarlo":2.0,"parejo":2.0,"cuidarse":2.0,"di":2.0,"miden":2.0,"influyentes":2.0,"dedicaban":2.0,"periodismo":6.0,"macana":4.0,"garrote":10.0,"estiraban":2.0,"das":2.0,"golpeadores":2.0,"duros":2.0,"pagando":2.0,"élite":2.0,"personajes":2.0,"buenísimos":2.0,"garrotazos":2.0,"someter":2.0,"zanahoria":2.0,"explicación":2.0,"aguantamos":2.0,"desequilibrio":4.0,"demos":2.0,"prefiero":2.0,"reclusorios":2.0,"Petróleos":2.0,"carro":4.0,"puros":2.0,"recuerde":2.0,"escuchara":2.0,"silenciarlos":2.0,"maicearlos":2.0,"inmoral":2.0,"dueños":4.0,"yate":6.0,"Saquen":2.0,"sexenio":2.0,"llega":2.0,"dimensionar":2.0,"reduciendo":2.0,"enojen":2.0,"insulten":2.0,"conmigo":2.0,"Manuelita":2.0,"apoyándome":2.0,"fraternas":2.0,"abnegadas":2.0,"Shaila":2.0,"Rosagel":2.0,"corresponsal":2.0,"grupo":6.0,"Healy":2.0,"Imparcial":2.0,"Mexicali":2.0,"Tijuana":6.0,"instaló":2.0,"pedazo":2.0,"muro":22.0,"Berlín":2.0,"Diego":2.0,"aspirante":4.0,"Marcelo":2.0,"Ebrard":2.0,"caer":2.0,"caiga":2.0,"contestado":2.0,"plateado":2.0,"pensaría":2.0,"boyas":8.0,"Texas":4.0,"envié":2.0,"acabo":4.0,"respetuoso":2.0,"agradeciendo":2.0,"últimamente":2.0,"mandó":2.0,"decidí":2.0,"escribirle":2.0,"mandarle":2.0,"tratando":2.0,"ofrezco":2.0,"Relaciones":2.0,"Washington":2.0,"aproveché":2.0,"traen":2.0,"informado":2.0,"África":2.0,"documentos":2.0,"legales":2.0,"detectan":2.0,"camiones":4.0,"casas":4.0,"Sonoyta":6.0,"Hermosillo":4.0,"delegado":2.0,"FGR":2.0,"reunir":2.0,"albergues":2.0,"escribo":2.0,"detenciones":2.0,"cuidando":2.0,"rescató":2.0,"frecuencia":2.0,"trasladan":2.0,"inseguros":2.0,"riesgoso":2.0,"periódicamente":2.0,"básicamente":8.0,"atribuye":2.0,"quieran":2.0,"analizando":2.0,"implementar":2.0,"Hablaba":2.0,"banca":2.0,"opcional":2.0,"forzosa":2.0,"reclamo":2.0,"ONU":2.0,"florero":2.0,"adorno":2.0,"causas":6.0,"darles":2.0,"atemperar":2.0,"consigan":2.0,"serenar":2.0,"siga":4.0,"droga":4.0,"bandas":2.0,"semilleros":2.0,"actos":2.0,"delictivos":2.0,"requiera":2.0,"medidas":2.0,"coercitivas":2.0,"bélico":2.0,"militarizando":2.0,"arcaico":2.0,"inhumano":2.0,"mentes":2.0,"autoritarias":2.0,"armamentista":2.0,"reunirnos":2.0,"gira":2.0,"tratarían":2.0,"supervisión":2.0,"Chica":2.0,"viaje":6.0,"patrias":2.0,"domingo":2.0,"posesión":2.0,"Alfredo":2.0,"Mazo":2.0,"inaugurar":2.0,"Toluca":2.0,"amigo":6.0,"saludarle":2.0,"honesta":2.0,"absoluta":2.0,"experta":2.0,"marchan":2.0,"tratado":2.0,"mutuamente":2.0,"Antony":2.0,"Blinken":2.0,"Jacke":2.0,"Sullivan":2.0,"servidores":2.0,"acordada":2.0,"Entendimiento":2.0,"Bicentenario":2.0,"Seguras":2.0,"obtenido":2.0,"valiosísima":2.0,"Sherwood":2.0,"dimensión":2.0,"humanitaria":2.0,"fentanilo":2.0,"formal":2.0,"ingresar":2.0,"legalmente":2.0,"cubanos":2.0,"haitianos":2.0,"venezolanos":2.0,"nicaragüenses":2.0,"actúa":2.0,"inhumana":2.0,"colocar":2.0,"alambres":2.0,"púas":2.0,"Bravo":2.0,"cuente":2.0,"informo":2.0,"recibí":2.0,"Cooperación":2.0,"Asía":2.0,"Pacífico":4.0,"volveremos":2.0,"obstante":2.0,"acordaba":2.0,"conversar":2.0,"saludarnos":2.0,"compañía":2.0,"Fortress":2.0,"instalando":2.0,"golfo":2.0,"exportar":2.0,"puerto":6.0,"Salina":4.0,"Cruz":2.0,"fondo":2.0,"danesa":2.0,"Copenhagen":2.0,"Infrastructure":2.0,"Partners":2.0,"hidrógeno":2.0,"barcos":2.0,"transiten":2.0,"mares":2.0,"contaminando":2.0,"hidrocarburos":2.0,"conociera":2.0,"sitio":2.0,"resume":2.0,"expondrá":2.0,"modernos":2.0,"turistas":2.0,"apreciar":2.0,"exuberante":2.0,"nativa":2.0,"hermoso":2.0,"litoral":2.0,"mar":2.0,"amiga":2.0,"Jill":2.0,"bienvenidos":2.0,"Saludos":2.0,"afectuosos":2.0,"admirable":2.0,"presidentes":4.0,"Clinton":2.0,"Bush":2.0,"padre":2.0,"Obama":2.0,"Trump":2.0,"antiinmigrantes":2.0,"deciden":2.0,"pura":2.0,"necesitan":2.0,"canta":4.0,"finado":2.0,"Pablo":2.0,"Milanés":2.0,"Silvio":2.0,"Busquen":2.0,"muralla":8.0,"Nicolás":2.0,"Guillén":2.0,"escucharlo":2.0,"abarque":2.0,"humilde":2.0,"facilitar":2.0,"depende":2.0,"utilice":2.0,"abrió":2.0,"reconociendo":2.0,"MUSICAL":2.0,"QUILAPAYÚN":2.0,"Eugenia":4.0,"oigo":2.0,"adiós":2.0,"Basta":4.0,"cumple":2.0,"felicidades":2.0,"periódico":2.0,"fotógrafos":2.0,"directivos":2.0,"GARCÍA VILCHIS":4.0,"People Media":10.0,"Transformación encabezada":4.0,"adultos mayores":6.0,"redes sociales":4.0,"Azucena Uresti":4.0,"Ciro Gómez":6.0,"Gómez Leyva":6.0,"Seguro Popular":6.0,"atención médica":6.0,"Felipe Calderón":4.0,"alimentación nutritiva":4.0,"Luis Cresencio":8.0,"Cresencio Sandoval":8.0,"listado nominal":6.0,"América Latina":6.0,"cada voto":8.0,"alta calidad":4.0,"zona conurbada":6.0,"San Luis":8.0,"Lord Molécula":4.0,"Molécula Oficial":4.0,"don Trino":4.0,"Comisión Federal":4.0,"Guardia Nacional":8.0,"Fuerza Aérea":10.0,"Relaciones Exteriores":4.0,"Alicia Bárcena":4.0,"maestra Delfina":6.0,"Chico Che":4.0,"destinaria":1.0}