{"Francisco": 2, "Villa": 2, "revolucionario": 1, "pueblo": 10, "Amigas": 1, "amigos": 2, "Xilitla": 9, "comunidades": 4, "región": 2, "autoridades": 1, "municipales": 2, "ejidales": 1, "gusto": 6, "nuevo": 3, "Huasteca": 15, "pendiente": 2, "compromiso": 2, "gira": 1, "grande": 3, "grandioso": 1, "país": 4, "costas": 1, "Valles": 3, "sierra": 1, "territorio": 1, "nacional": 1, "visitando": 1, "supervisando": 1, "orden": 1, "dada": 1, "supervisada": 1, "sirve": 1, "Venimos": 1, "informarles": 1, "primero": 3, "continuar": 10, "Bienestar": 8, "expresó": 1, "Carlos": 4, "Torres": 1, "coordinador": 1, "gobierno": 8, "República": 1, "Empiezo": 1, "decirles": 1, "mencionó": 2, "ampliar": 1, "mejorar": 1, "programa": 24, "pensión": 6, "informo": 1, "hizo": 1, "mención": 1, "enero": 1, "próximo": 3, "aumenta": 1, "termine": 1, "mandato": 1, "septiembre": 1, "pueda": 2, "ir": 11, "entusiasmo": 1, "interior": 1, "fortaleza": 1, "moral": 1, "menos": 1, "alcanzar": 2, "par": 1, "esposos": 1, "ancianos": 1, "puedan": 3, "alimentación": 1, "importante": 3, "elevó": 1, "rango": 1, "constitucional": 1, "Constitución": 2, "artículo": 2, "4º": 1, "quedó": 1, "establecido": 1, "trata": 1, "derecho": 1, "Presidencia": 1, "seguir": 6, "otorgando": 1, "apoyo": 9, "Incluso": 1, "misma": 1, "conoce": 1, "establece": 1, "aumentando": 2, "monto": 1, "destinado": 1, "razones": 2, "rápido": 1, "expreso": 1, "terminar": 2, "ciclo": 1, "tranquilo": 2, "partidario": 1, "sufragio": 1, "efectivo": 1, "reelección": 1, "maderista": 1, "Segundo": 1, "relevo": 1, "puedo": 1, "cualquiera": 2, "sustituirme": 1, "capacidad": 1, "conozco": 2, "garantizar": 1, "continuidad": 1, "cambio": 1, "tercero": 1, "asunto": 1, "íntimo": 1, "criterio": 1, "tenerle": 2, "apego": 2, "cariño": 1, "poder": 3, "dinero": 1, "felicidad": 4, "verdadera": 1, "bien": 8, "mismo": 3, "consciencia": 2, "prójimo": 1, "verdad": 2, "gobernador": 1, "Ricardo": 1, "Gallardo": 1, "aceptado": 2, "propuesta": 1, "hicimos": 2, "cuatro": 3, "años": 8, "discapacidad": 1, "sólo": 5, "otorgaba": 1, "niñas": 2, "adolescentes": 3, "pobres": 2, "discapacitado": 2, "recibía": 1, "propusimos": 1, "gobernadores": 1, "mayoría": 2, "aceptó": 1, "trato": 1, "federal": 1, "aportará": 1, "universal": 1, "jóvenes": 10, "Construyendo": 4, "Futuro": 3, "dijo": 2, "explicó": 1, "responsable": 2, "Marath": 1, "trabajando": 5, "volteaba": 1, "ofendía": 1, "ninis": 1, "estudian": 2, "trabajan": 2, "manera": 4, "despectiva": 1, "joven": 2, "oportunidad": 3, "trabajo": 7, "estudiando": 2, "trabajar": 1, "aprendiz": 1, "taller": 2, "tienda": 1, "campo": 2, "artesanía": 1, "equivalente": 1, "salario": 4, "mínimo": 2, "poca": 1, "cosa": 4, "tiempo": 4, "aumentado": 2, "pesos": 6, "términos": 1, "reales": 1, "casi": 1, "sucedía": 1, "veía": 1, "aumentaba": 2, "veces": 4, "inflación": 1, "llevaba": 1, "pérdida": 1, "compra": 1, "alcanzaba": 1, "ingreso": 1, "siquiera": 1, "indispensable": 1, "encampanen": 1, "sonsaquen": 1, "enganchen": 1, "lleven": 1, "delincuencia": 1, "estudio": 2, "resolviendo": 1, "problema": 4, "inseguridad": 1, "violencia": 3, "enfrentar": 1, "querer": 2, "apagar": 1, "fuego": 2, "mal": 1, "enfrentarlo": 1, "haciendo": 3, "paz": 1, "fruto": 1, "justicia": 1, "fortalecer": 3, "valores": 4, "culturales": 3, "cierto": 2, "vinieron": 1, "españoles": 1, "europeos": 2, "civilizarnos": 1, "llegaran": 1, "florecido": 1, "civilizaciones": 1, "culturas": 3, "profundo": 1, "raíces": 1, "profundas": 1, "podido": 1, "salir": 2, "adelante": 2, "frente": 1, "adversidades": 1, "protegido": 2, "salvado": 1, "calamidades": 1, "inundaciones": 1, "temblores": 1, "pandemias": 1, "siempre": 3, "renace": 1, "avergonzarnos": 1, "pasado": 1, "contrario": 1, "identidad": 1, "sabe": 2, "dónde": 3, "viene": 2, "saber": 1, "nunca": 3, "hacia": 1, "estarnos": 1, "avergonzando": 1, "apenando": 1, "tradiciones": 1, "costumbres": 1, "lenguas": 1, "Organización": 6, "social": 2, "lejos": 1, "mantener": 2, "gran": 2, "reserva": 1, "morales": 1, "espirituales": 1, "ayuda": 1, "damos": 1, "cuenta": 3, "conferencias": 1, "menciono": 1, "respeto": 2, "vida": 4, "países": 1, "Unidos": 6, "ejemplo": 2, "digo": 2, "respetuosa": 1, "creciendo": 1, "casa": 7, "leí": 1, "padres": 3, "mamá": 2, "papá": 1, "acusar": 1, "hijo": 4, "autoridad": 1, "juez": 2, "cumplido": 1, "quería": 1, "dio": 1, "razón": 1, "papas": 1, "sucede": 1, "vayan": 2, "abusan": 1, "quedan": 1, "todavía": 2, "casan": 1, "solar": 1, "amplía": 1, "nietos": 1, "acostumbrados": 1, "malo": 2, "mantiene": 1, "familia": 7, "unidad": 1, "desintegrada": 1, "señores": 1, "Texas": 1, "decían": 4, "video": 1, "diciendo": 1, "informando": 1, "comentaba": 1, "buscaran": 1, "irse": 1, "querían": 1, "viviendo": 1, "aportar": 1, "dólares": 3, "mensuales": 1, "aprender": 1, "cuesta": 2, "pensar": 2, "afortunadamente": 3, "decimos": 1, "quédense": 1, "encuentran": 1, "échenles": 1, "agua": 1, "frijoles": 1, "integración": 1, "institución": 1, "seguridad": 2, "afectando": 1, "mundo": 2, "drogadicción": 2, "consumo": 2, "adicción": 1, "lamentablemente": 1, "perdiendo": 1, "personas": 1, "cada": 8, "grave": 1, "orientar": 1, "alejen": 1, "opciones": 1, "decide": 1, "camino": 1, "solo": 1, "apapacho": 1, "vacío": 1, "cree": 1, "droga": 2, "encontrar": 3, "efímero": 1, "transitorio": 2, "lleva": 1, "infelicidad": 1, "dejar": 1, "herencia": 1, "recibimos": 1, "antepasados": 1, "preescolar": 1, "primaria": 1, "secundaria": 1, "entregando": 4, "estudiantes": 1, "educación": 1, "media": 1, "superior": 1, "bachiller": 1, "preparatoria": 1, "licenciatura": 2, "universidad": 3, "medicina": 2, "contabilidad": 1, "ingeniería": 1, "cualquier": 1, "carrera": 1, "nivel": 1, "universitario": 1, "hablaba": 1, "Benito": 1, "Juárez": 1, "crear": 2, "llegar": 5, "universidades": 1, "dedicadas": 1, "enfermería": 1, "productores": 4, "conocía": 1, "Procampo": 1, "llegaba": 1, "machuchones": 1, "caciques": 1, "corruptos": 1, "llega": 4, "campesinos": 2, "abajo": 3, "recibiendo": 3, "directa": 1, "sucursales": 7, "Banco": 10, "tarjeta": 3, "sacar": 3, "corresponde": 2, "intermediarios": 1, "Independiente": 1, "Popular": 1, "Emiliano": 1, "Zapata": 1, "Ponciano": 1, "Arriaga": 1, "primo": 1, "hermano": 1, "acabó": 2, "entregar": 2, "organizaciones": 2, "directo": 2, "entrega": 1, "muchas": 2, "moche": 1, "piquete": 1, "ojo": 1, "millones": 8, "beneficiarios": 1, "municipio": 2, "sucursal": 3, "cerca": 1, "apartadas": 2, "gente": 4, "trasladarse": 1, "recoger": 2, "quiero": 1, "agradecer": 1, "Secretaría": 1, "Defensa": 1, "ingenieros": 1, "militares": 1, "potosina": 1, "quiere": 1, "cabeceras": 1, "adulto": 1, "mayor": 1, "beca": 5, "recurso": 2, "Sembrando": 3, "dispersar": 1, "red": 1, "manejar": 1, "promedio": 2, "reactiva": 1, "economía": 2, "llegan": 1, "enviando": 2, "paisanos": 2, "migrantes": 1, "aplauso": 2, "envían": 2, "familiares": 2, "Saben": 2, "cifra": 1, "récord": 1, "mayo": 1, "estimamos": 1, "cinco": 1, "mes": 1, "pasar": 1, "regiones": 1, "reactivan": 1, "circulante": 1, "crisis": 1, "básico": 1, "poquito": 1, "llamados": 1, "neoliberales": 1, "neoporfiristas": 1, "clave": 1, "mañosa": 1, "truco": 1, "ayudar": 1, "arriba": 2, "llueve": 1, "gotea": 1, "lluvia": 1, "permeable": 1, "contagiosa": 1, "Aunque": 1, "llueva": 1, "fuerte": 1, "cae": 1, "queda": 1, "hojas": 1, "copa": 1, "vaso": 4, "derrama": 1, "derramar": 1, "llena": 2, "ponen": 1, "derramaba": 1, "época": 1, "elecciones": 1, "repartían": 1, "migajas": 1, "dádivas": 1, "despensas": 1, "frijol": 2, "gorgojo": 1, "materiales": 1, "construcción": 2, "tierra": 1, "candidatos": 1, "pollos": 1, "patos": 1, "borregos": 1, "chivos": 1, "puercos": 1, "cochinos": 1, "marranos": 1, "tráfico": 1, "pobreza": 1, "empoderó": 1, "pueden": 1, "repartir": 1, "preocupes": 1, "seguro": 1, "voto": 1, "hora": 1, "votar": 1, "toma": 1, "Champotón": 1, "vote": 1, "dicte": 1, "mujeres": 1, "libres": 1, "Precios": 3, "Garantía": 2, "justos": 1, "maíz": 1, "producen": 2, "leche": 1, "alimentos": 1, "mejoramiento": 1, "reconstrucción": 1, "vivienda": 1, "aplicando": 1, "jornal": 1, "siembren": 1, "árboles": 1, "frutales": 1, "maderables": 1, "parcelas": 1, "ejidos": 1, "pequeñas": 1, "propiedades": 1, "aproveche": 1, "sembrar": 2, "pensando": 1, "aprovechen": 1, "falta": 1, "mejor": 2, "cambiar": 1, "mientras": 1, "aprovechar": 1, "creo": 1, "fácil": 1, "quitar": 1, "sembradores": 1, "millón": 1, "hectáreas": 1, "general": 1, "ayudando": 1, "Ejército": 1, "vivero": 3, "obteniendo": 1, "plantas": 1, "comunitarios": 1, "doy": 1, "buena": 2, "noticia": 1, "empezar": 1, "fertilizantes": 2, "gratuitos": 1, "Escuela": 2, "presupuesto": 2, "sociedades": 1, "madres": 1, "hagan": 1, "cargo": 1, "condiciones": 1, "planteles": 1, "educativos": 1, "compañera": 1, "Pamela": 1, "ampliación": 1, "carretera": 3, "Tamazunchale": 2, "dato": 1, "invirtiendo": 1, "carriles": 1, "paga": 1, "marzo": 1, "autorizaron": 1, "adicionales": 1, "falte": 1, "venir": 2, "regresar": 1, "volver": 2, "Déjenme": 1, "sentirse": 1, "bellos": 1, "sureste": 1, "paraíso": 1, "edén": 1, "toda": 3, "lugar": 1, "místico": 1, "dormido": 1, "descansado": 1, "descansar": 1, "obra": 4, "arte": 2, "surrealista": 3, "única": 1, "ojalá": 1, "visitarla": 1, "visitar": 1, "centro": 1, "cultural": 1, "museo": 1, "surrealismo": 1, "interpretar": 1, "tan": 1, "simple": 2, "sencillo": 1, "permite": 1, "desarrollar": 1, "mente": 1, "imaginar": 1, "subiendo": 1, "escaleras": 1, "llevan": 1, "aparentemente": 1, "ninguna": 1, "parte": 2, "encantador": 1, "finado": 1, "director": 2, "Vizuet": 6, "Policía": 1, "Bancaria": 1, "jefe": 1, "Ciudad": 1, "anda": 1, "adelantó": 1, "sigue": 1, "originaria": 1, "Rodríguez": 1, "secretaria": 1, "sabían": 1, "maestra": 1, "crió": 1, "Axtla": 1, "mandamos": 1, "saludo": 1, "invitamos": 1, "cuidando": 2, "asaltos": 1, "robos": 1, "dejamos": 1, "gobernar": 1, "velar": 1, "quedamos": 1, "inauguración": 1, "recuento": 1, "funcionando": 1, "regrese": 2, "recibido": 1, "avanzando": 1, "adultos mayores": 7, "San Luis": 4, "Luis Potosí": 4, "seguir apoyando": 3, "Rosa Icela": 3}